Workbook

Sheet Orders
A1: order_id | B1: supplier_id | C1: product_id | D1: quantity | E1: order_date | F1: Order_date_
A2: 3999 | B2: 49 | C2: 36 | D2: 17 | E2: 45217 | F2: 45217
A3: 3995 | B3: 28 | C3: 199 | D3: 35 | E3: 45142 | F3: 45142
A4: 3994 | B4: 49 | C4: 130 | D4: 14 | E4: 45046 | F4: 45046
A5: 3992 | B5: 39 | C5: 87 | D5: 62 | E5: 45118 | F5: 45118
A6: 5 | B6: 1 | C6: 108 | D6: 63 | E6: 45101 | F6: 45101
A7: 6 | B7: 28 | C7: 93 | D7: 82 | E7: 44981 | F7: 44981
A8: 3988 | B8: 12 | C8: 193 | D8: 3 | E8: 45206 | F8: 45206
A9: 8 | B9: 47 | C9: 134 | D9: 84 | E9: 45017 | F9: 45017
A10: 3982 | B10: 37 | C10: 97 | D10: 85 | E10: 45117 | F10: 45117
A11: 3975 | B11: 44 | C11: 74 | D11: 27 | E11: 45257 | F11: 45257
A12: 3968 | B12: 19 | C12: 67 | D12: 90 | E12: 45017 | F12: 45017
A13: 3967 | B13: 13 | C13: 70 | D13: 26 | E13: 45042 | F13: 45042
... A1227: 1226 | B1227: 44 | C1227: 109 | D1227: 14 | E1227: 45036 | F1227: 45036

Sheet Clean_Processing
A1: order_id | B1: supplier_id | C1: product_id | D1: quantity | E1: Order_date2 | F1: Year | G1: Product_name | H1: Supplier_name | I1: Product Category | J1: Vehicle Id | K1: Vehicle type | L1: Delivery_date | M1: Delivery_status | N1: Delivery_cost $ | O1: Delivery_profit $ | P1: Delivery _profit_margin% | Q1: Unit_cost $ | R1: Total_revenue $ | S1: Profit $ | T1: Profit_margin% | U1: Delivery_days | V1: Delivery_rate | W1: Destination_city
A2: 1 | B2: 50 | C2: 78 | D2: 88 | E2: 45283 | F2: 2023 | G2: =INDEX(Products!B:B, MATCH(C2,Clean_Processing!A:A, 0)) -> Enter | H2: =INDEX(Suppliers!B:B, MATCH(B2, Clean_Processing!A:A, 0)) -> Waters-Robinson | I2: =INDEX(Products!C:C, MATCH(B2,Clean_Processing!A:A, 0)) -> Medical | J2: =INDEX(Shipments!C:C, MATCH(B2,Clean_Processing!A:A, 0)) -> 9 | K2: =INDEX(Shipments!D:D, MATCH(C2,Clean_Processing!A:A, 0)) -> Drone | L2: 45044 | M2: Delivered | N2: =IFERROR(INDEX(Shipments!G:G, MATCH(J2, Clean_Processing!C:C, 0)), "") -> 398.406 | O2: 10767.034 | P2: 0.96431793 | Q2: =INDEX(Products!D:D, MATCH(C2, Clean_Processing!A:A, 0)) -> 126.88 | R2: 11165.44 | S2: 10640.154 | T2: 0.95295429 | W2: Crystalland
A3: 2 | B3: 8 | C3: 145 | D3: 6 | E3: 45234 | F3: 2023 | G3: =INDEX(Products!B:B, MATCH(C3,Clean_Processing!A:A, 0)) -> Economic | H3: =INDEX(Suppliers!B:B, MATCH(B3, Clean_Processing!A:A, 0)) -> Andrews-Jordan | I3: =INDEX(Products!C:C, MATCH(B3,Clean_Processing!A:A, 0)) -> Medical | J3: =INDEX(Shipments!C:C, MATCH(B3,Clean_Processing!A:A, 0)) -> 27 | K3: =INDEX(Shipments!D:D, MATCH(C3,Clean_Processing!A:A, 0)) -> Van | L3: 45156 | M3: Delivered | N3: =IFERROR(INDEX(Shipments!G:G, MATCH(J3, Clean_Processing!C:C, 0)), "") -> 49.753309 | O3: 420.10669 | P3: 0.89411035 | Q3: =INDEX(Products!D:D, MATCH(C3, Clean_Processing!A:A, 0)) -> 78.31 | R3: 469.86 | S3: 341.79669 | T3: 0.72744369 | W3: North Stephanie
A4: 3 | B4: 35 | C4: 110 | D4: 85 | E4: 45104 | F4: 2023 | G4: =INDEX(Products!B:B, MATCH(C4,Clean_Processing!A:A, 0)) -> Thousand | H4: =INDEX(Suppliers!B:B, MATCH(B4, Clean_Processing!A:A, 0)) -> Braun-Miller | I4: =INDEX(Products!C:C, MATCH(B4,Clean_Processing!A:A, 0)) -> Food | J4: =INDEX(Shipments!C:C, MATCH(B4,Clean_Processing!A:A, 0)) -> 68 | K4: =INDEX(Shipments!D:D, MATCH(C4,Clean_Processing!A:A, 0)) -> 0 | L4: 45120 | M4: Delivered | N4: =IFERROR(INDEX(Shipments!G:G, MATCH(J4, Clean_Processing!C:C, 0)), "") -> 74.899801 | O4: 679.0502 | P4: 0.90065681 | Q4: =INDEX(Products!D:D, MATCH(C4, Clean_Processing!A:A, 0)) -> 8.87 | R4: 753.95 | S4: 670.1802 | T4: 0.8888921 | U4: 16 | V4: Slow | W4: Kellyside
A5: 4 | B5: 5 | C5: 130 | D5: 83 | E5: 45116 | F5: 2023 | G5: =INDEX(Products!B:B, MATCH(C5,Clean_Processing!A:A, 0)) -> Three | H5: =INDEX(Suppliers!B:B, MATCH(B5, Clean_Processing!A:A, 0)) -> Logan-Fernandez | I5: =INDEX(Products!C:C, MATCH(B5,Clean_Processing!A:A, 0)) -> Clothing | J5: =INDEX(Shipments!C:C, MATCH(B5,Clean_Processing!A:A, 0)) -> 44 | K5: =INDEX(Shipments!D:D, MATCH(C5,Clean_Processing!A:A, 0)) -> 0 | L5: 45273 | M5: Delivered | N5: =IFERROR(INDEX(Shipments!G:G, MATCH(J5, Clean_Processing!C:C, 0)), "") -> 454.92062 | O5: 11327.759 | P5: 0.96139073 | Q5: =INDEX(Products!D:D, MATCH(C5, Clean_Processing!A:A, 0)) -> 141.96 | R5: 11782.68 | S5: 11185.799 | T5: 0.94934254 | U5: 157 | V5: Slow | W5: West Kirk
A6: 5 | B6: 1 | C6: 108 | D6: 63 | E6: 45101 | F6: 2023 | G6: =INDEX(Products!B:B, MATCH(C6,Clean_Processing!A:A, 0)) -> Interesting | H6: =INDEX(Suppliers!B:B, MATCH(B6, Clean_Processing!A:A, 0)) -> Robinson, Beasley and Hall | I6: =INDEX(Products!C:C, MATCH(B6,Clean_Processing!A:A, 0)) -> Electronics | J6: =INDEX(Shipments!C:C, MATCH(B6,Clean_Processing!A:A, 0)) -> 28 | K6: =INDEX(Shipments!D:D, MATCH(C6,Clean_Processing!A:A, 0)) -> 0 | L6: 45090 | M6: Delivered | N6: =IFERROR(INDEX(Shipments!G:G, MATCH(J6, Clean_Processing!C:C, 0)), "") -> 362.48678 | O6: 30739.353 | P6: 0.98834517 | Q6: =INDEX(Products!D:D, MATCH(C6, Clean_Processing!A:A, 0)) -> 493.68 | R6: 31101.84 | S6: 30245.673 | T6: 0.97247215 | W6: West Lindsey
A7: 6 | B7: 28 | C7: 93 | D7: 82 | E7: 44981 | F7: 2023 | G7: =INDEX(Products!B:B, MATCH(C7,Clean_Processing!A:A, 0)) -> Local | H7: =INDEX(Suppliers!B:B, MATCH(B7, Clean_Processing!A:A, 0)) -> Brown, Maynard and Campbell | I7: =INDEX(Products!C:C, MATCH(B7,Clean_Processing!A:A, 0)) -> Electronics | J7: =INDEX(Shipments!C:C, MATCH(B7,Clean_Processing!A:A, 0)) -> 66 | K7: =INDEX(Shipments!D:D, MATCH(C7,Clean_Processing!A:A, 0)) -> Bike | L7: 45237 | M7: Delivered | N7: =IFERROR(INDEX(Shipments!G:G, MATCH(J7, Clean_Processing!C:C, 0)), "") -> 194.08343 | O7: 3160.5366 | P7: 0.94214444 | Q7: =INDEX(Products!D:D, MATCH(C7, Clean_Processing!A:A, 0)) -> 40.91 | R7: 3354.62 | S7: 3119.6266 | T7: 0.92994931 | U7: 256 | V7: Slow | W7: Port Marybury
A8: 7 | B8: 46 | C8: 40 | D8: 56 | E8: 45162 | F8: 2023 | G8: =INDEX(Products!B:B, MATCH(C8,Clean_Processing!A:A, 0)) -> Individual | H8: =INDEX(Suppliers!B:B, MATCH(B8, Clean_Processing!A:A, 0)) -> Bailey PLC | I8: =INDEX(Products!C:C, MATCH(B8,Clean_Processing!A:A, 0)) -> Medical | J8: =INDEX(Shipments!C:C, MATCH(B8,Clean_Processing!A:A, 0)) -> 19 | K8: =INDEX(Shipments!D:D, MATCH(C8,Clean_Processing!A:A, 0)) -> Drone | L8: 45286 | M8: Delivered | N8: =IFERROR(INDEX(Shipments!G:G, MATCH(J8, Clean_Processing!C:C, 0)), "") -> 194.0078 | O8: 23260.472 | P8: 0.99172833 | Q8: =INDEX(Products!D:D, MATCH(C8, Clean_Processing!A:A, 0)) -> 418.83 | R8: 23454.48 | S8: 22841.642 | T8: 0.97387118 | U8: 124 | V8: Slow | W8: North Amber
A9: 8 | B9: 47 | C9: 134 | D9: 84 | E9: 45017 | F9: 2023 | G9: =INDEX(Products!B:B, MATCH(C9,Clean_Processing!A:A, 0)) -> Traditional | H9: =INDEX(Suppliers!B:B, MATCH(B9, Clean_Processing!A:A, 0)) -> Gutierrez and Sons | I9: =INDEX(Products!C:C, MATCH(B9,Clean_Processing!A:A, 0)) -> Electronics | J9: =INDEX(Shipments!C:C, MATCH(B9,Clean_Processing!A:A, 0)) -> 45 | K9: =INDEX(Shipments!D:D, MATCH(C9,Clean_Processing!A:A, 0)) -> Bike | L9: 45039 | M9: Delivered | N9: =IFERROR(INDEX(Shipments!G:G, MATCH(J9, Clean_Processing!C:C, 0)), "") -> 207.67191 | O9: 11104.608 | P9: 0.98164191 | Q9: =INDEX(Products!D:D, MATCH(C9, Clean_Processing!A:A, 0)) -> 134.67 | R9: 11312.28 | S9: 10969.938 | T9: 0.96973714 | U9: 22 | V9: Slow | W9: West James
A10: 9 | B10: 40 | C10: 138 | D10: 100 | E10: 45065 | F10: 2023 | G10: =INDEX(Products!B:B, MATCH(C10,Clean_Processing!A:A, 0)) -> Choose | H10: =INDEX(Suppliers!B:B, MATCH(B10, Clean_Processing!A:A, 0)) -> Ross Inc | I10: =INDEX(Products!C:C, MATCH(B10,Clean_Processing!A:A, 0)) -> Food | J10: =INDEX(Shipments!C:C, MATCH(B10,Clean_Processing!A:A, 0)) -> 48 | K10: =INDEX(Shipments!D:D, MATCH(C10,Clean_Processing!A:A, 0)) -> 0 | L10: 45075 | M10: Delivered | N10: =IFERROR(INDEX(Shipments!G:G, MATCH(J10, Clean_Processing!C:C, 0)), "") -> 438.83986 | O10: 540.16014 | P10: 0.55174682 | Q10: =INDEX(Products!D:D, MATCH(C10, Clean_Processing!A:A, 0)) -> 9.79 | R10: 979 | S10: 530.37014 | T10: 0.54174682 | U10: 10 | V10: Normal | W10: New Harold
A11: 10 | B11: 30 | C11: 112 | D11: 94 | E11: 45174 | F11: 2023 | G11: =INDEX(Products!B:B, MATCH(C11,Clean_Processing!A:A, 0)) -> Among | H11: =INDEX(Suppliers!B:B, MATCH(B11, Clean_Processing!A:A, 0)) -> Burton-Logan | I11: =INDEX(Products!C:C, MATCH(B11,Clean_Processing!A:A, 0)) -> Furniture | J11: =INDEX(Shipments!C:C, MATCH(B11,Clean_Processing!A:A, 0)) -> 17 | K11: =INDEX(Shipments!D:D, MATCH(C11,Clean_Processing!A:A, 0)) -> 0 | L11: 45281 | M11: Delivered | N11: =IFERROR(INDEX(Shipments!G:G, MATCH(J11, Clean_Processing!C:C, 0)), "") -> 480.10591 | O11: 13919.754 | P11: 0.96665899 | Q11: =INDEX(Products!D:D, MATCH(C11, Clean_Processing!A:A, 0)) -> 153.19 | R11: 14399.86 | S11: 13766.564 | T11: 0.95602069 | U11: 107 | V11: Slow | W11: West Tara
A12: 11 | B12: 18 | C12: 83 | D12: 32 | E12: 45230 | F12: 2023 | G12: =INDEX(Products!B:B, MATCH(C12,Clean_Processing!A:A, 0)) -> Resource | H12: =INDEX(Suppliers!B:B, MATCH(B12, Clean_Processing!A:A, 0)) -> Walsh and Sons | I12: =INDEX(Products!C:C, MATCH(B12,Clean_Processing!A:A, 0)) -> Medical | J12: =INDEX(Shipments!C:C, MATCH(B12,Clean_Processing!A:A, 0)) -> 7 | K12: =INDEX(Shipments!D:D, MATCH(C12,Clean_Processing!A:A, 0)) -> Bike | L12: 45291 | M12: Delivered | N12: =IFERROR(INDEX(Shipments!G:G, MATCH(J12, Clean_Processing!C:C, 0)), "") -> 277.62922 | O12: 8163.3308 | P12: 0.96710928 | Q12: =INDEX(Products!D:D, MATCH(C12, Clean_Processing!A:A, 0)) -> 263.78 | R12: 8440.96 | S12: 7899.5508 | T12: 0.93585928 | U12: 61 | V12: Slow | W12: Austinstad
A13: 12 | B13: 18 | C13: 116 | D13: 32 | E13: 44971 | F13: 2023 | G13: =INDEX(Products!B:B, MATCH(C13,Clean_Processing!A:A, 0)) -> Suffer | H13: =INDEX(Suppliers!B:B, MATCH(B13, Clean_Processing!A:A, 0)) -> Walsh and Sons | I13: =INDEX(Products!C:C, MATCH(B13,Clean_Processing!A:A, 0)) -> Medical | J13: =INDEX(Shipments!C:C, MATCH(B13,Clean_Processing!A:A, 0)) -> 7 | K13: =INDEX(Shipments!D:D, MATCH(C13,Clean_Processing!A:A, 0)) -> Bike | L13: 45121 | M13: Delivered | N13: =IFERROR(INDEX(Shipments!G:G, MATCH(J13, Clean_Processing!C:C, 0)), "") -> 277.62922 | O13: 1710.8508 | P13: 0.86038118 | Q13: =INDEX(Products!D:D, MATCH(C13, Clean_Processing!A:A, 0)) -> 62.14 | R13: 1988.48 | S13: 1648.7108 | T13: 0.82913118 | U13: 150 | V13: Slow | W13: Timothyland
A14: 13 | B14: 37 | C14: 157 | D14: 86 | E14: 45164 | F14: 2023 | G14: =INDEX(Products!B:B, MATCH(C14,Clean_Processing!A:A, 0)) -> On | H14: =INDEX(Suppliers!B:B, MATCH(B14, Clean_Processing!A:A, 0)) -> Butler Ltd | I14: =INDEX(Products!C:C, MATCH(B14,Clean_Processing!A:A, 0)) -> Electronics | J14: =INDEX(Shipments!C:C, MATCH(B14,Clean_Processing!A:A, 0)) -> 22 | K14: =INDEX(Shipments!D:D, MATCH(C14,Clean_Processing!A:A, 0)) -> Bike | L14: 44974 | M14: Delivered | N14: =IFERROR(INDEX(Shipments!G:G, MATCH(J14, Clean_Processing!C:C, 0)), "") -> 461.69547 | O14: 17268.065 | P14: 0.97395929 | Q14: =INDEX(Products!D:D, MATCH(C14, Clean_Processing!A:A, 0)) -> 206.16 | R14: 17729.76 | S14: 17061.905 | T14: 0.96233139 | W14: New Jerome
A15: 14 | B15: 22 | C15: 8 | D15: 64 | E15: 45121 | F15: 2023 | G15: =INDEX(Products!B:B, MATCH(C15,Clean_Processing!A:A, 0)) -> Science | H15: =INDEX(Suppliers!B:B, MATCH(B15, Clean_Processing!A:A, 0)) -> Martinez PLC | I15: =INDEX(Products!C:C, MATCH(B15,Clean_Processing!A:A, 0)) -> Medical | J15: =INDEX(Shipments!C:C, MATCH(B15,Clean_Processing!A:A, 0)) -> 74 | K15: =INDEX(Shipments!D:D, MATCH(C15,Clean_Processing!A:A, 0)) -> Drone | L15: 45115 | M15: Delivered | N15: =IFERROR(INDEX(Shipments!G:G, MATCH(J15, Clean_Processing!C:C, 0)), "") -> 131.6184 | O15: 21381.342 | P15: 0.9938819 | Q15: =INDEX(Products!D:D, MATCH(C15, Clean_Processing!A:A, 0)) -> 336.14 | R15: 21512.96 | S15: 21045.202 | T15: 0.9782569 | W15: Gonzalesstad
A16: 15 | B16: 12 | C16: 125 | D16: 28 | E16: 45093 | F16: 2023 | G16: =INDEX(Products!B:B, MATCH(C16,Clean_Processing!A:A, 0)) -> Hold | H16: =INDEX(Suppliers!B:B, MATCH(B16, Clean_Processing!A:A, 0)) -> Yoder-Thompson | I16: =INDEX(Products!C:C, MATCH(B16,Clean_Processing!A:A, 0)) -> Electronics | J16: =INDEX(Shipments!C:C, MATCH(B16,Clean_Processing!A:A, 0)) -> 47 | K16: =INDEX(Shipments!D:D, MATCH(C16,Clean_Processing!A:A, 0)) -> Van | L16: 45229 | M16: Delivered | N16: =IFERROR(INDEX(Shipments!G:G, MATCH(J16, Clean_Processing!C:C, 0)), "") -> 119.57635 | O16: 6791.3836 | P16: 0.98269758 | Q16: =INDEX(Products!D:D, MATCH(C16, Clean_Processing!A:A, 0)) -> 246.82 | R16: 6910.96 | S16: 6544.5636 | T16: 0.94698329 | U16: 136 | V16: Slow | W16: Hugheston
A17: 16 | B17: 17 | C17: 88 | D17: 36 | E17: 45108 | F17: 2023 | G17: =INDEX(Products!B:B, MATCH(C17,Clean_Processing!A:A, 0)) -> City | H17: =INDEX(Suppliers!B:B, MATCH(B17, Clean_Processing!A:A, 0)) -> Acevedo PLC | I17: =INDEX(Products!C:C, MATCH(B17,Clean_Processing!A:A, 0)) -> Medical | J17: =INDEX(Shipments!C:C, MATCH(B17,Clean_Processing!A:A, 0)) -> 12 | K17: =INDEX(Shipments!D:D, MATCH(C17,Clean_Processing!A:A, 0)) -> Bike | L17: 45123 | M17: Delivered | N17: =IFERROR(INDEX(Shipments!G:G, MATCH(J17, Clean_Processing!C:C, 0)), "") -> 435.71256 | O17: 6797.0474 | P17: 0.93975847 | Q17: =INDEX(Products!D:D, MATCH(C17, Clean_Processing!A:A, 0)) -> 200.91 | R17: 7232.76 | S17: 6596.1374 | T17: 0.91198069 | U17: 15 | V17: Slow | W17: North Austinton
A18: 17 | B18: 45 | C18: 71 | D18: 72 | E18: 45232 | F18: 2023 | G18: =INDEX(Products!B:B, MATCH(C18,Clean_Processing!A:A, 0)) -> Much | H18: =INDEX(Suppliers!B:B, MATCH(B18, Clean_Processing!A:A, 0)) -> Horton-Huffman | I18: =INDEX(Products!C:C, MATCH(B18,Clean_Processing!A:A, 0)) -> Furniture | J18: =INDEX(Shipments!C:C, MATCH(B18,Clean_Processing!A:A, 0)) -> 60 | K18: =INDEX(Shipments!D:D, MATCH(C18,Clean_Processing!A:A, 0)) -> Bike | L18: 45289 | M18: Delivered | N18: =IFERROR(INDEX(Shipments!G:G, MATCH(J18, Clean_Processing!C:C, 0)), "") -> 257.20978 | O18: 2958.3102 | P18: 0.9200099 | Q18: =INDEX(Products!D:D, MATCH(C18, Clean_Processing!A:A, 0)) -> 44.66 | R18: 3215.52 | S18: 2913.6502 | T18: 0.90612101 | U18: 57 | V18: Slow | W18: Lake Christopher
A19: 18 | B19: 34 | C19: 49 | D19: 11 | E19: 44932 | F19: 2023 | G19: =INDEX(Products!B:B, MATCH(C19,Clean_Processing!A:A, 0)) -> Ability | H19: =INDEX(Suppliers!B:B, MATCH(B19, Clean_Processing!A:A, 0)) -> Singh Ltd | I19: =INDEX(Products!C:C, MATCH(B19,Clean_Processing!A:A, 0)) -> Clothing | J19: =INDEX(Shipments!C:C, MATCH(B19,Clean_Processing!A:A, 0)) -> 68 | K19: =INDEX(Shipments!D:D, MATCH(C19,Clean_Processing!A:A, 0)) -> Drone | L19: 45054 | M19: Delivered | N19: =IFERROR(INDEX(Shipments!G:G, MATCH(J19, Clean_Processing!C:C, 0)), "") -> 74.899801 | O19: 2043.5902 | P19: 0.96464472 | Q19: =INDEX(Products!D:D, MATCH(C19, Clean_Processing!A:A, 0)) -> 192.59 | R19: 2118.49 | S19: 1851.0002 | T19: 0.87373563 | U19: 122 | V19: Slow | W19: Port Stevenberg
A20: 19 | B20: 47 | C20: 105 | D20: 63 | E20: 45050 | F20: 2023 | G20: =INDEX(Products!B:B, MATCH(C20,Clean_Processing!A:A, 0)) -> Herself | H20: =INDEX(Suppliers!B:B, MATCH(B20, Clean_Processing!A:A, 0)) -> Gutierrez and Sons | I20: =INDEX(Products!C:C, MATCH(B20,Clean_Processing!A:A, 0)) -> Electronics | J20: =INDEX(Shipments!C:C, MATCH(B20,Clean_Processing!A:A, 0)) -> 45 | K20: =INDEX(Shipments!D:D, MATCH(C20,Clean_Processing!A:A, 0)) -> 0 | L20: 45004 | M20: Delivered | N20: =IFERROR(INDEX(Shipments!G:G, MATCH(J20, Clean_Processing!C:C, 0)), "") -> 207.67191 | O20: 26107.428 | P20: 0.99210826 | Q20: =INDEX(Products!D:D, MATCH(C20, Clean_Processing!A:A, 0)) -> 417.7 | R20: 26315.1 | S20: 25689.728 | T20: 0.97623524 | W20: West Lisa
A21: 20 | B21: 49 | C21: 62 | D21: 89 | E21: 45211 | F21: 2023 | G21: =INDEX(Products!B:B, MATCH(C21,Clean_Processing!A:A, 0)) -> Even | H21: =INDEX(Suppliers!B:B, MATCH(B21, Clean_Processing!A:A, 0)) -> Hawkins Inc | I21: =INDEX(Products!C:C, MATCH(B21,Clean_Processing!A:A, 0)) -> Electronics | J21: =INDEX(Shipments!C:C, MATCH(B21,Clean_Processing!A:A, 0)) -> 71 | K21: =INDEX(Shipments!D:D, MATCH(C21,Clean_Processing!A:A, 0)) -> Van | L21: 45022 | M21: Delivered | N21: =IFERROR(INDEX(Shipments!G:G, MATCH(J21, Clean_Processing!C:C, 0)), "") -> 55.264623 | O21: 25905.145 | P21: 0.9978712 | Q21: =INDEX(Products!D:D, MATCH(C21, Clean_Processing!A:A, 0)) -> 291.69 | R21: 25960.41 | S21: 25613.455 | T21: 0.98663524 | W21: Welchborough
A22: 21 | B22: 42 | C22: 183 | D22: 63 | E22: 45170 | F22: 2023 | G22: =INDEX(Products!B:B, MATCH(C22,Clean_Processing!A:A, 0)) -> Trip | H22: =INDEX(Suppliers!B:B, MATCH(B22, Clean_Processing!A:A, 0)) -> Sullivan-Smith | I22: =INDEX(Products!C:C, MATCH(B22,Clean_Processing!A:A, 0)) -> Medical | J22: =INDEX(Shipments!C:C, MATCH(B22,Clean_Processing!A:A, 0)) -> 98 | K22: =INDEX(Shipments!D:D, MATCH(C22,Clean_Processing!A:A, 0)) -> 0 | L22: 44961 | M22: Delivered | N22: =IFERROR(INDEX(Shipments!G:G, MATCH(J22, Clean_Processing!C:C, 0)), "") -> 419.97811 | O22: 632.75189 | P22: 0.60105809 | Q22: =INDEX(Products!D:D, MATCH(C22, Clean_Processing!A:A, 0)) -> 16.71 | R22: 1052.73 | S22: 616.04189 | T22: 0.58518508 | W22: Lake Bethany
A23: 22 | B23: 2 | C23: 24 | D23: 38 | E23: 45156 | F23: 2023 | G23: =INDEX(Products!B:B, MATCH(C23,Clean_Processing!A:A, 0)) -> Message | H23: =INDEX(Suppliers!B:B, MATCH(B23, Clean_Processing!A:A, 0)) -> Holmes, Duncan and Reed | I23: =INDEX(Products!C:C, MATCH(B23,Clean_Processing!A:A, 0)) -> Electronics | J23: =INDEX(Shipments!C:C, MATCH(B23,Clean_Processing!A:A, 0)) -> 92 | K23: =INDEX(Shipments!D:D, MATCH(C23,Clean_Processing!A:A, 0)) -> Van | L23: 45262 | M23: Delivered | N23: =IFERROR(INDEX(Shipments!G:G, MATCH(J23, Clean_Processing!C:C, 0)), "") -> 455.91997 | O23: 1585.44 | P23: 0.77665871 | Q23: =INDEX(Products!D:D, MATCH(C23, Clean_Processing!A:A, 0)) -> 53.72 | R23: 2041.36 | S23: 1531.72 | T23: 0.75034292 | U23: 106 | V23: Slow | W23: Port Micheleland
A24: 23 | B24: 26 | C24: 178 | D24: 32 | E24: 45040 | F24: 2023 | G24: =INDEX(Products!B:B, MATCH(C24,Clean_Processing!A:A, 0)) -> Magazine | H24: =INDEX(Suppliers!B:B, MATCH(B24, Clean_Processing!A:A, 0)) -> Miller-Pennington | I24: =INDEX(Products!C:C, MATCH(B24,Clean_Processing!A:A, 0)) -> Medical | J24: =INDEX(Shipments!C:C, MATCH(B24,Clean_Processing!A:A, 0)) -> 71 | K24: =INDEX(Shipments!D:D, MATCH(C24,Clean_Processing!A:A, 0)) -> Bike | L24: 45012 | M24: Delivered | N24: =IFERROR(INDEX(Shipments!G:G, MATCH(J24, Clean_Processing!C:C, 0)), "") -> 55.264623 | O24: 13039.455 | P24: 0.99577963 | Q24: =INDEX(Products!D:D, MATCH(C24, Clean_Processing!A:A, 0)) -> 409.21 | R24: 13094.72 | S24: 12630.245 | T24: 0.96452963 | W24: New Ericfort
A25: 24 | B25: 43 | C25: 149 | D25: 48 | E25: 45083 | F25: 2023 | G25: =INDEX(Products!B:B, MATCH(C25,Clean_Processing!A:A, 0)) -> Subject | H25: =INDEX(Suppliers!B:B, MATCH(B25, Clean_Processing!A:A, 0)) -> Johnson, Knight and Dawson | I25: =INDEX(Products!C:C, MATCH(B25,Clean_Processing!A:A, 0)) -> Food | J25: =INDEX(Shipments!C:C, MATCH(B25,Clean_Processing!A:A, 0)) -> 3 | K25: =INDEX(Shipments!D:D, MATCH(C25,Clean_Processing!A:A, 0)) -> 0 | L25: 45290 | M25: Delivered | N25: =IFERROR(INDEX(Shipments!G:G, MATCH(J25, Clean_Processing!C:C, 0)), "") -> 254.79639 | O25: 18901.044 | P25: 0.98669876 | Q25: =INDEX(Products!D:D, MATCH(C25, Clean_Processing!A:A, 0)) -> 399.08 | R25: 19155.84 | S25: 18501.964 | T25: 0.96586543 | U25: 207 | V25: Slow | W25: Spencermouth
A26: 25 | B26: 36 | C26: 136 | D26: 45 | E26: 45169 | F26: 2023 | G26: =INDEX(Products!B:B, MATCH(C26,Clean_Processing!A:A, 0)) -> Product | H26: =INDEX(Suppliers!B:B, MATCH(B26, Clean_Processing!A:A, 0)) -> Petersen Inc | I26: =INDEX(Products!C:C, MATCH(B26,Clean_Processing!A:A, 0)) -> Electronics | J26: =INDEX(Shipments!C:C, MATCH(B26,Clean_Processing!A:A, 0)) -> 74 | K26: =INDEX(Shipments!D:D, MATCH(C26,Clean_Processing!A:A, 0)) -> 0 | L26: 45021 | M26: Delivered | N26: =IFERROR(INDEX(Shipments!G:G, MATCH(J26, Clean_Processing!C:C, 0)), "") -> 131.6184 | O26: 12381.982 | P26: 0.98948197 | Q26: =INDEX(Products!D:D, MATCH(C26, Clean_Processing!A:A, 0)) -> 278.08 | R26: 12513.6 | S26: 12103.902 | T26: 0.96725975 | W26: Port Kimberly
A27: 26 | B27: 48 | C27: 141 | D27: 43 | E27: 45144 | F27: 2023 | G27: =INDEX(Products!B:B, MATCH(C27,Clean_Processing!A:A, 0)) -> Interesting | H27: =INDEX(Suppliers!B:B, MATCH(B27, Clean_Processing!A:A, 0)) -> Thompson, Shaw and Brown | I27: =INDEX(Products!C:C, MATCH(B27,Clean_Processing!A:A, 0)) -> Furniture | J27: =INDEX(Shipments!C:C, MATCH(B27,Clean_Processing!A:A, 0)) -> 10 | K27: =INDEX(Shipments!D:D, MATCH(C27,Clean_Processing!A:A, 0)) -> Bike | L27: 45115 | M27: Delivered | N27: =IFERROR(INDEX(Shipments!G:G, MATCH(J27, Clean_Processing!C:C, 0)), "") -> 445.89732 | O27: 19009.023 | P27: 0.97708049 | Q27: =INDEX(Products!D:D, MATCH(C27, Clean_Processing!A:A, 0)) -> 452.44 | R27: 19454.92 | S27: 18556.583 | T27: 0.95382467 | W27: Grahamfort
A28: 27 | B28: 45 | C28: 117 | D28: 35 | E28: 45107 | F28: 2023 | G28: =INDEX(Products!B:B, MATCH(C28,Clean_Processing!A:A, 0)) -> Girl | H28: =INDEX(Suppliers!B:B, MATCH(B28, Clean_Processing!A:A, 0)) -> Horton-Huffman | I28: =INDEX(Products!C:C, MATCH(B28,Clean_Processing!A:A, 0)) -> Furniture | J28: =INDEX(Shipments!C:C, MATCH(B28,Clean_Processing!A:A, 0)) -> 60 | K28: =INDEX(Shipments!D:D, MATCH(C28,Clean_Processing!A:A, 0)) -> Truck | L28: 44932 | M28: Delivered | N28: =IFERROR(INDEX(Shipments!G:G, MATCH(J28, Clean_Processing!C:C, 0)), "") -> 257.20978 | O28: 1772.0902 | P28: 0.87325197 | Q28: =INDEX(Products!D:D, MATCH(C28, Clean_Processing!A:A, 0)) -> 57.98 | R28: 2029.3 | S28: 1714.1102 | T28: 0.84468054 | W28: North April
A29: 28 | B29: 17 | C29: 60 | D29: 16 | E29: 45083 | F29: 2023 | G29: =INDEX(Products!B:B, MATCH(C29,Clean_Processing!A:A, 0)) -> Including | H29: =INDEX(Suppliers!B:B, MATCH(B29, Clean_Processing!A:A, 0)) -> Acevedo PLC | I29: =INDEX(Products!C:C, MATCH(B29,Clean_Processing!A:A, 0)) -> Medical | J29: =INDEX(Shipments!C:C, MATCH(B29,Clean_Processing!A:A, 0)) -> 12 | K29: =INDEX(Shipments!D:D, MATCH(C29,Clean_Processing!A:A, 0)) -> Bike | L29: 44940 | M29: Delivered | N29: =IFERROR(INDEX(Shipments!G:G, MATCH(J29, Clean_Processing!C:C, 0)), "") -> 435.71256 | O29: 1994.2074 | P29: 0.82068852 | Q29: =INDEX(Products!D:D, MATCH(C29, Clean_Processing!A:A, 0)) -> 151.87 | R29: 2429.92 | S29: 1842.3374 | T29: 0.75818852 | W29: Garciahaven
A30: 29 | B30: 21 | C30: 31 | D30: 96 | E30: 45025 | F30: 2023 | G30: =INDEX(Products!B:B, MATCH(C30,Clean_Processing!A:A, 0)) -> Last | H30: =INDEX(Suppliers!B:B, MATCH(B30, Clean_Processing!A:A, 0)) -> Delgado Ltd | I30: =INDEX(Products!C:C, MATCH(B30,Clean_Processing!A:A, 0)) -> Clothing | J30: =INDEX(Shipments!C:C, MATCH(B30,Clean_Processing!A:A, 0)) -> 67 | K30: =INDEX(Shipments!D:D, MATCH(C30,Clean_Processing!A:A, 0)) -> Bike | L30: 44996 | M30: Delivered | N30: =IFERROR(INDEX(Shipments!G:G, MATCH(J30, Clean_Processing!C:C, 0)), "") -> 289.43524 | O30: 20238.245 | P30: 0.98590025 | Q30: =INDEX(Products!D:D, MATCH(C30, Clean_Processing!A:A, 0)) -> 213.83 | R30: 20527.68 | S30: 20024.415 | T30: 0.97548358 | W30: South Ravenstad
A31: 30 | B31: 49 | C31: 177 | D31: 24 | E31: 45201 | F31: 2023 | G31: =INDEX(Products!B:B, MATCH(C31,Clean_Processing!A:A, 0)) -> Any | H31: =INDEX(Suppliers!B:B, MATCH(B31, Clean_Processing!A:A, 0)) -> Hawkins Inc | I31: =INDEX(Products!C:C, MATCH(B31,Clean_Processing!A:A, 0)) -> Electronics | J31: =INDEX(Shipments!C:C, MATCH(B31,Clean_Processing!A:A, 0)) -> 71 | K31: =INDEX(Shipments!D:D, MATCH(C31,Clean_Processing!A:A, 0)) -> Van | L31: 45053 | M31: Delivered | N31: =IFERROR(INDEX(Shipments!G:G, MATCH(J31, Clean_Processing!C:C, 0)), "") -> 55.264623 | O31: 2707.1354 | P31: 0.97999398 | Q31: =INDEX(Products!D:D, MATCH(C31, Clean_Processing!A:A, 0)) -> 115.1 | R31: 2762.4 | S31: 2592.0354 | T31: 0.93832732 | W31: Riosview
A32: 31 | B32: 14 | C32: 190 | D32: 62 | E32: 45025 | F32: 2023 | G32: =INDEX(Products!B:B, MATCH(C32,Clean_Processing!A:A, 0)) -> Listen | H32: =INDEX(Suppliers!B:B, MATCH(B32, Clean_Processing!A:A, 0)) -> Walsh-Perez | I32: =INDEX(Products!C:C, MATCH(B32,Clean_Processing!A:A, 0)) -> Electronics | J32: =INDEX(Shipments!C:C, MATCH(B32,Clean_Processing!A:A, 0)) -> 35 | K32: =INDEX(Shipments!D:D, MATCH(C32,Clean_Processing!A:A, 0)) -> Van | L32: 45163 | M32: Delivered | N32: =IFERROR(INDEX(Shipments!G:G, MATCH(J32, Clean_Processing!C:C, 0)), "") -> 330.20981 | O32: 12245.87 | P32: 0.97374303 | Q32: =INDEX(Products!D:D, MATCH(C32, Clean_Processing!A:A, 0)) -> 202.84 | R32: 12576.08 | S32: 12043.03 | T32: 0.95761399 | U32: 138 | V32: Slow | W32: Robertstad
A33: 32 | B33: 47 | C33: 151 | D33: 98 | E33: 45068 | F33: 2023 | G33: =INDEX(Products!B:B, MATCH(C33,Clean_Processing!A:A, 0)) -> Mother | H33: =INDEX(Suppliers!B:B, MATCH(B33, Clean_Processing!A:A, 0)) -> Gutierrez and Sons | I33: =INDEX(Products!C:C, MATCH(B33,Clean_Processing!A:A, 0)) -> Electronics | J33: =INDEX(Shipments!C:C, MATCH(B33,Clean_Processing!A:A, 0)) -> 45 | K33: =INDEX(Shipments!D:D, MATCH(C33,Clean_Processing!A:A, 0)) -> Bike | L33: 45054 | M33: Delivered | N33: =IFERROR(INDEX(Shipments!G:G, MATCH(J33, Clean_Processing!C:C, 0)), "") -> 207.67191 | O33: 43889.388 | P33: 0.99529057 | Q33: =INDEX(Products!D:D, MATCH(C33, Clean_Processing!A:A, 0)) -> 449.97 | R33: 44097.06 | S33: 43439.418 | T33: 0.98508649 | W33: Samueltown
A34: 33 | B34: 39 | C34: 73 | D34: 13 | E34: 45195 | F34: 2023 | G34: =INDEX(Products!B:B, MATCH(C34,Clean_Processing!A:A, 0)) -> Attorney | H34: =INDEX(Suppliers!B:B, MATCH(B34, Clean_Processing!A:A, 0)) -> Garcia-Logan | I34: =INDEX(Products!C:C, MATCH(B34,Clean_Processing!A:A, 0)) -> Electronics | J34: =INDEX(Shipments!C:C, MATCH(B34,Clean_Processing!A:A, 0)) -> 15 | K34: =INDEX(Shipments!D:D, MATCH(C34,Clean_Processing!A:A, 0)) -> Drone | L34: 45120 | M34: Delivered | N34: =IFERROR(INDEX(Shipments!G:G, MATCH(J34, Clean_Processing!C:C, 0)), "") -> 99.677513 | O34: 3794.3425 | P34: 0.97440241 | Q34: =INDEX(Products!D:D, MATCH(C34, Clean_Processing!A:A, 0)) -> 299.54 | R34: 3894.02 | S34: 3494.8025 | T34: 0.89747934 | W34: New Madison
A35: 34 | B35: 19 | C35: 59 | D35: 47 | E35: 45026 | F35: 2023 | G35: =INDEX(Products!B:B, MATCH(C35,Clean_Processing!A:A, 0)) -> Play | H35: =INDEX(Suppliers!B:B, MATCH(B35, Clean_Processing!A:A, 0)) -> King LLC | I35: =INDEX(Products!C:C, MATCH(B35,Clean_Processing!A:A, 0)) -> Electronics | J35: =INDEX(Shipments!C:C, MATCH(B35,Clean_Processing!A:A, 0)) -> 58 | K35: =INDEX(Shipments!D:D, MATCH(C35,Clean_Processing!A:A, 0)) -> Van | L35: 45179 | M35: Delivered | N35: =IFERROR(INDEX(Shipments!G:G, MATCH(J35, Clean_Processing!C:C, 0)), "") -> 444.6528 | O35: 3391.4872 | P35: 0.88408849 | Q35: =INDEX(Products!D:D, MATCH(C35, Clean_Processing!A:A, 0)) -> 81.62 | R35: 3836.14 | S35: 3309.8672 | T35: 0.86281189 | U35: 153 | V35: Slow | W35: South Tylerstad
A36: 35 | B36: 20 | C36: 4 | D36: 91 | E36: 45018 | F36: 2023 | G36: =INDEX(Products!B:B, MATCH(C36,Clean_Processing!A:A, 0)) -> Step | H36: =INDEX(Suppliers!B:B, MATCH(B36, Clean_Processing!A:A, 0)) -> Cooper-Jones | I36: =INDEX(Products!C:C, MATCH(B36,Clean_Processing!A:A, 0)) -> Medical | J36: =INDEX(Shipments!C:C, MATCH(B36,Clean_Processing!A:A, 0)) -> 36 | K36: =INDEX(Shipments!D:D, MATCH(C36,Clean_Processing!A:A, 0)) -> Drone | L36: 45168 | M36: Delivered | N36: =IFERROR(INDEX(Shipments!G:G, MATCH(J36, Clean_Processing!C:C, 0)), "") -> 177.62958 | O36: 41061.75 | P36: 0.99569272 | Q36: =INDEX(Products!D:D, MATCH(C36, Clean_Processing!A:A, 0)) -> 453.18 | R36: 41239.38 | S36: 40608.57 | T36: 0.98470371 | U36: 150 | V36: Slow | W36: New Briannabury
A37: 36 | B37: 9 | C37: 71 | D37: 6 | E37: 45200 | F37: 2023 | G37: =INDEX(Products!B:B, MATCH(C37,Clean_Processing!A:A, 0)) -> Much | H37: =INDEX(Suppliers!B:B, MATCH(B37, Clean_Processing!A:A, 0)) -> Aguirre and Sons | I37: =INDEX(Products!C:C, MATCH(B37,Clean_Processing!A:A, 0)) -> Electronics | J37: =INDEX(Shipments!C:C, MATCH(B37,Clean_Processing!A:A, 0)) -> 32 | K37: =INDEX(Shipments!D:D, MATCH(C37,Clean_Processing!A:A, 0)) -> Bike | L37: 45135 | M37: Delivered | N37: =IFERROR(INDEX(Shipments!G:G, MATCH(J37, Clean_Processing!C:C, 0)), "") -> 173.69079 | O37: 94.269213 | P37: 0.3518033 | Q37: =INDEX(Products!D:D, MATCH(C37, Clean_Processing!A:A, 0)) -> 44.66 | R37: 267.96 | S37: 49.609213 | T37: 0.18513664 | W37: Evansberg
A38: 37 | B38: 36 | C38: 75 | D38: 90 | E38: 44954 | F38: 2023 | G38: =INDEX(Products!B:B, MATCH(C38,Clean_Processing!A:A, 0)) -> People | H38: =INDEX(Suppliers!B:B, MATCH(B38, Clean_Processing!A:A, 0)) -> Petersen Inc | I38: =INDEX(Products!C:C, MATCH(B38,Clean_Processing!A:A, 0)) -> Electronics | J38: =INDEX(Shipments!C:C, MATCH(B38,Clean_Processing!A:A, 0)) -> 74 | K38: =INDEX(Shipments!D:D, MATCH(C38,Clean_Processing!A:A, 0)) -> Drone | L38: 45186 | M38: Delivered | N38: =IFERROR(INDEX(Shipments!G:G, MATCH(J38, Clean_Processing!C:C, 0)), "") -> 131.6184 | O38: 10797.082 | P38: 0.98795663 | Q38: =INDEX(Products!D:D, MATCH(C38, Clean_Processing!A:A, 0)) -> 121.43 | R38: 10928.7 | S38: 10675.652 | T38: 0.97684552 | U38: 232 | V38: Slow | W38: Port Arthurfort
A39: 38 | B39: 41 | C39: 193 | D39: 63 | E39: 44991 | F39: 2023 | G39: =INDEX(Products!B:B, MATCH(C39,Clean_Processing!A:A, 0)) -> Hold | H39: =INDEX(Suppliers!B:B, MATCH(B39, Clean_Processing!A:A, 0)) -> Gomez and Sons | I39: =INDEX(Products!C:C, MATCH(B39,Clean_Processing!A:A, 0)) -> Food | J39: =INDEX(Shipments!C:C, MATCH(B39,Clean_Processing!A:A, 0)) -> 28 | K39: =INDEX(Shipments!D:D, MATCH(C39,Clean_Processing!A:A, 0)) -> 0 | L39: 44967 | M39: Delivered | N39: =IFERROR(INDEX(Shipments!G:G, MATCH(J39, Clean_Processing!C:C, 0)), "") -> 362.48678 | O39: 29242.473 | P39: 0.98775588 | Q39: =INDEX(Products!D:D, MATCH(C39, Clean_Processing!A:A, 0)) -> 469.92 | R39: 29604.96 | S39: 28772.553 | T39: 0.97188286 | W39: Marcusfort
A40: 39 | B40: 1 | C40: 147 | D40: 37 | E40: 44979 | F40: 2023 | G40: =INDEX(Products!B:B, MATCH(C40,Clean_Processing!A:A, 0)) -> Congress | H40: =INDEX(Suppliers!B:B, MATCH(B40, Clean_Processing!A:A, 0)) -> Robinson, Beasley and Hall | I40: =INDEX(Products!C:C, MATCH(B40,Clean_Processing!A:A, 0)) -> Electronics | J40: =INDEX(Shipments!C:C, MATCH(B40,Clean_Processing!A:A, 0)) -> 28 | K40: =INDEX(Shipments!D:D, MATCH(C40,Clean_Processing!A:A, 0)) -> Drone | L40: 45238 | M40: Delivered | N40: =IFERROR(INDEX(Shipments!G:G, MATCH(J40, Clean_Processing!C:C, 0)), "") -> 362.48678 | O40: 5468.3432 | P40: 0.93783273 | Q40: =INDEX(Products!D:D, MATCH(C40, Clean_Processing!A:A, 0)) -> 157.59 | R40: 5830.83 | S40: 5310.7532 | T40: 0.9108057 | U40: 259 | V40: Slow | W40: North Stephanieside
A41: 40 | B41: 31 | C41: 113 | D41: 44 | E41: 45167 | F41: 2023 | G41: =INDEX(Products!B:B, MATCH(C41,Clean_Processing!A:A, 0)) -> Right | H41: =INDEX(Suppliers!B:B, MATCH(B41, Clean_Processing!A:A, 0)) -> Turner LLC | I41: =INDEX(Products!C:C, MATCH(B41,Clean_Processing!A:A, 0)) -> Food | J41: =INDEX(Shipments!C:C, MATCH(B41,Clean_Processing!A:A, 0)) -> 36 | K41: =INDEX(Shipments!D:D, MATCH(C41,Clean_Processing!A:A, 0)) -> Truck | L41: 44940 | M41: Delivered | N41: =IFERROR(INDEX(Shipments!G:G, MATCH(J41, Clean_Processing!C:C, 0)), "") -> 177.62958 | O41: 14491.09 | P41: 0.98789059 | Q41: =INDEX(Products!D:D, MATCH(C41, Clean_Processing!A:A, 0)) -> 333.38 | R41: 14668.72 | S41: 14157.71 | T41: 0.96516331 | W41: Greenstad
A42: 41 | B42: 4 | C42: 65 | D42: 62 | E42: 45021 | F42: 2023 | G42: =INDEX(Products!B:B, MATCH(C42,Clean_Processing!A:A, 0)) -> Probably | H42: =INDEX(Suppliers!B:B, MATCH(B42, Clean_Processing!A:A, 0)) -> Martin, Dean and Glenn | I42: =INDEX(Products!C:C, MATCH(B42,Clean_Processing!A:A, 0)) -> Clothing | J42: =INDEX(Shipments!C:C, MATCH(B42,Clean_Processing!A:A, 0)) -> 27 | K42: =INDEX(Shipments!D:D, MATCH(C42,Clean_Processing!A:A, 0)) -> Truck | L42: 45149 | M42: Delivered | N42: =IFERROR(INDEX(Shipments!G:G, MATCH(J42, Clean_Processing!C:C, 0)), "") -> 49.753309 | O42: 2014.8467 | P42: 0.97590172 | Q42: =INDEX(Products!D:D, MATCH(C42, Clean_Processing!A:A, 0)) -> 33.3 | R42: 2064.6 | S42: 1981.5467 | T42: 0.95977269 | U42: 128 | V42: Slow | W42: East Robertbury
A43: 42 | B43: 5 | C43: 103 | D43: 63 | E43: 44985 | F43: 2023 | G43: =INDEX(Products!B:B, MATCH(C43,Clean_Processing!A:A, 0)) -> Scientist | H43: =INDEX(Suppliers!B:B, MATCH(B43, Clean_Processing!A:A, 0)) -> Logan-Fernandez | I43: =INDEX(Products!C:C, MATCH(B43,Clean_Processing!A:A, 0)) -> Clothing | J43: =INDEX(Shipments!C:C, MATCH(B43,Clean_Processing!A:A, 0)) -> 44 | K43: =INDEX(Shipments!D:D, MATCH(C43,Clean_Processing!A:A, 0)) -> Drone | L43: 44999 | M43: Delivered | N43: =IFERROR(INDEX(Shipments!G:G, MATCH(J43, Clean_Processing!C:C, 0)), "") -> 454.92062 | O43: 11384.039 | P43: 0.96157428 | Q43: =INDEX(Products!D:D, MATCH(C43, Clean_Processing!A:A, 0)) -> 187.92 | R43: 11838.96 | S43: 11196.119 | T43: 0.94570126 | U43: 14 | V43: Normal | W43: Lake Robertberg
A44: 43 | B44: 37 | C44: 162 | D44: 88 | E44: 44964 | F44: 2023 | G44: =INDEX(Products!B:B, MATCH(C44,Clean_Processing!A:A, 0)) -> Step | H44: =INDEX(Suppliers!B:B, MATCH(B44, Clean_Processing!A:A, 0)) -> Butler Ltd | I44: =INDEX(Products!C:C, MATCH(B44,Clean_Processing!A:A, 0)) -> Electronics | J44: =INDEX(Shipments!C:C, MATCH(B44,Clean_Processing!A:A, 0)) -> 22 | K44: =INDEX(Shipments!D:D, MATCH(C44,Clean_Processing!A:A, 0)) -> 0 | L44: 45045 | M44: Delivered | N44: =IFERROR(INDEX(Shipments!G:G, MATCH(J44, Clean_Processing!C:C, 0)), "") -> 461.69547 | O44: 42501.665 | P44: 0.98925374 | Q44: =INDEX(Products!D:D, MATCH(C44, Clean_Processing!A:A, 0)) -> 488.22 | R44: 42963.36 | S44: 42013.445 | T44: 0.9778901 | U44: 81 | V44: Slow | W44: Phillipsville
A45: 44 | B45: 10 | C45: 39 | D45: 73 | E45: 44954 | F45: 2023 | G45: =INDEX(Products!B:B, MATCH(C45,Clean_Processing!A:A, 0)) -> Able | H45: =INDEX(Suppliers!B:B, MATCH(B45, Clean_Processing!A:A, 0)) -> Wilson, Jones and Gregory | I45: =INDEX(Products!C:C, MATCH(B45,Clean_Processing!A:A, 0)) -> Medical | J45: =INDEX(Shipments!C:C, MATCH(B45,Clean_Processing!A:A, 0)) -> 4 | K45: =INDEX(Shipments!D:D, MATCH(C45,Clean_Processing!A:A, 0)) -> Van | L45: 45293 | M45: Delivered | N45: =IFERROR(INDEX(Shipments!G:G, MATCH(J45, Clean_Processing!C:C, 0)), "") -> 183.42839 | O45: 36290.292 | P45: 0.99497094 | Q45: =INDEX(Products!D:D, MATCH(C45, Clean_Processing!A:A, 0)) -> 499.64 | R45: 36473.72 | S45: 35790.652 | T45: 0.98127231 | U45: 339 | V45: Slow | W45: West Benjamin
A46: 45 | B46: 6 | C46: 64 | D46: 16 | E46: 45082 | F46: 2023 | G46: =INDEX(Products!B:B, MATCH(C46,Clean_Processing!A:A, 0)) -> Effort | H46: =INDEX(Suppliers!B:B, MATCH(B46, Clean_Processing!A:A, 0)) -> Dunn Ltd | I46: =INDEX(Products!C:C, MATCH(B46,Clean_Processing!A:A, 0)) -> Clothing | J46: =INDEX(Shipments!C:C, MATCH(B46,Clean_Processing!A:A, 0)) -> 57 | K46: =INDEX(Shipments!D:D, MATCH(C46,Clean_Processing!A:A, 0)) -> Truck | L46: 44995 | M46: Delivered | N46: =IFERROR(INDEX(Shipments!G:G, MATCH(J46, Clean_Processing!C:C, 0)), "") -> 68.653463 | O46: 5935.3465 | P46: 0.98856538 | Q46: =INDEX(Products!D:D, MATCH(C46, Clean_Processing!A:A, 0)) -> 375.25 | R46: 6004 | S46: 5560.0965 | T46: 0.92606538 | W46: Lake Scott
A47: 46 | B47: 49 | C47: 107 | D47: 78 | E47: 45212 | F47: 2023 | G47: =INDEX(Products!B:B, MATCH(C47,Clean_Processing!A:A, 0)) -> Billion | H47: =INDEX(Suppliers!B:B, MATCH(B47, Clean_Processing!A:A, 0)) -> Hawkins Inc | I47: =INDEX(Products!C:C, MATCH(B47,Clean_Processing!A:A, 0)) -> Electronics | J47: =INDEX(Shipments!C:C, MATCH(B47,Clean_Processing!A:A, 0)) -> 71 | K47: =INDEX(Shipments!D:D, MATCH(C47,Clean_Processing!A:A, 0)) -> 0 | L47: 45253 | M47: Delivered | N47: =IFERROR(INDEX(Shipments!G:G, MATCH(J47, Clean_Processing!C:C, 0)), "") -> 55.264623 | O47: 23951.575 | P47: 0.99769796 | Q47: =INDEX(Products!D:D, MATCH(C47, Clean_Processing!A:A, 0)) -> 307.78 | R47: 24006.84 | S47: 23643.795 | T47: 0.98487745 | U47: 41 | V47: Slow | W47: Brownborough
A48: 47 | B48: 40 | C48: 58 | D48: 100 | E48: 45232 | F48: 2023 | G48: =INDEX(Products!B:B, MATCH(C48,Clean_Processing!A:A, 0)) -> Even | H48: =INDEX(Suppliers!B:B, MATCH(B48, Clean_Processing!A:A, 0)) -> Ross Inc | I48: =INDEX(Products!C:C, MATCH(B48,Clean_Processing!A:A, 0)) -> Food | J48: =INDEX(Shipments!C:C, MATCH(B48,Clean_Processing!A:A, 0)) -> 48 | K48: =INDEX(Shipments!D:D, MATCH(C48,Clean_Processing!A:A, 0)) -> Van | L48: 45167 | M48: Delivered | N48: =IFERROR(INDEX(Shipments!G:G, MATCH(J48, Clean_Processing!C:C, 0)), "") -> 438.83986 | O48: 35622.16 | P48: 0.98783062 | Q48: =INDEX(Products!D:D, MATCH(C48, Clean_Processing!A:A, 0)) -> 360.61 | R48: 36061 | S48: 35261.55 | T48: 0.97783062 | W48: Hollowayview
A49: 48 | B49: 25 | C49: 116 | D49: 57 | E49: 45194 | F49: 2023 | G49: =INDEX(Products!B:B, MATCH(C49,Clean_Processing!A:A, 0)) -> Suffer | H49: =INDEX(Suppliers!B:B, MATCH(B49, Clean_Processing!A:A, 0)) -> Kim-Cole | I49: =INDEX(Products!C:C, MATCH(B49,Clean_Processing!A:A, 0)) -> Furniture | J49: =INDEX(Shipments!C:C, MATCH(B49,Clean_Processing!A:A, 0)) -> 35 | K49: =INDEX(Shipments!D:D, MATCH(C49,Clean_Processing!A:A, 0)) -> Bike | L49: 45234 | M49: Delivered | N49: =IFERROR(INDEX(Shipments!G:G, MATCH(J49, Clean_Processing!C:C, 0)), "") -> 330.20981 | O49: 3211.7702 | P49: 0.90677254 | Q49: =INDEX(Products!D:D, MATCH(C49, Clean_Processing!A:A, 0)) -> 62.14 | R49: 3541.98 | S49: 3149.6302 | T49: 0.88922868 | U49: 40 | V49: Slow | W49: Rodneyberg
A50: 49 | B50: 38 | C50: 110 | D50: 40 | E50: 45079 | F50: 2023 | G50: =INDEX(Products!B:B, MATCH(C50,Clean_Processing!A:A, 0)) -> Thousand | H50: =INDEX(Suppliers!B:B, MATCH(B50, Clean_Processing!A:A, 0)) -> Gray Group | I50: =INDEX(Products!C:C, MATCH(B50,Clean_Processing!A:A, 0)) -> Furniture | J50: =INDEX(Shipments!C:C, MATCH(B50,Clean_Processing!A:A, 0)) -> 27 | K50: =INDEX(Shipments!D:D, MATCH(C50,Clean_Processing!A:A, 0)) -> 0 | L50: 45170 | M50: Delivered | N50: =IFERROR(INDEX(Shipments!G:G, MATCH(J50, Clean_Processing!C:C, 0)), "") -> 49.753309 | O50: 305.04669 | P50: 0.85977083 | Q50: =INDEX(Products!D:D, MATCH(C50, Clean_Processing!A:A, 0)) -> 8.87 | R50: 354.8 | S50: 296.17669 | T50: 0.83477083 | U50: 91 | V50: Slow | W50: South Joseph
A51: 50 | B51: 40 | C51: 16 | D51: 79 | E51: 45218 | F51: 2023 | G51: =INDEX(Products!B:B, MATCH(C51,Clean_Processing!A:A, 0)) -> Back | H51: =INDEX(Suppliers!B:B, MATCH(B51, Clean_Processing!A:A, 0)) -> Ross Inc | I51: =INDEX(Products!C:C, MATCH(B51,Clean_Processing!A:A, 0)) -> Food | J51: =INDEX(Shipments!C:C, MATCH(B51,Clean_Processing!A:A, 0)) -> 48 | K51: =INDEX(Shipments!D:D, MATCH(C51,Clean_Processing!A:A, 0)) -> Truck | L51: 45108 | M51: Delivered | N51: =IFERROR(INDEX(Shipments!G:G, MATCH(J51, Clean_Processing!C:C, 0)), "") -> 438.83986 | O51: 7401.9101 | P51: 0.94403088 | Q51: =INDEX(Products!D:D, MATCH(C51, Clean_Processing!A:A, 0)) -> 99.25 | R51: 7840.75 | S51: 7302.6601 | T51: 0.93137265 | W51: North Bradley
A52: 51 | B52: 49 | C52: 54 | D52: 81 | E52: 44977 | F52: 2023 | G52: =INDEX(Products!B:B, MATCH(C52,Clean_Processing!A:A, 0)) -> Shake | H52: =INDEX(Suppliers!B:B, MATCH(B52, Clean_Processing!A:A, 0)) -> Hawkins Inc | I52: =INDEX(Products!C:C, MATCH(B52,Clean_Processing!A:A, 0)) -> Electronics | J52: =INDEX(Shipments!C:C, MATCH(B52,Clean_Processing!A:A, 0)) -> 71 | K52: =INDEX(Shipments!D:D, MATCH(C52,Clean_Processing!A:A, 0)) -> Bike | L52: 44931 | M52: Delivered | N52: =IFERROR(INDEX(Shipments!G:G, MATCH(J52, Clean_Processing!C:C, 0)), "") -> 55.264623 | O52: 17310.325 | P52: 0.99681758 | Q52: =INDEX(Products!D:D, MATCH(C52, Clean_Processing!A:A, 0)) -> 214.39 | R52: 17365.59 | S52: 17095.935 | T52: 0.9844719 | W52: Lake Miguel
A53: 52 | B53: 17 | C53: 170 | D53: 11 | E53: 45035 | F53: 2023 | G53: =INDEX(Products!B:B, MATCH(C53,Clean_Processing!A:A, 0)) -> Arm | H53: =INDEX(Suppliers!B:B, MATCH(B53, Clean_Processing!A:A, 0)) -> Acevedo PLC | I53: =INDEX(Products!C:C, MATCH(B53,Clean_Processing!A:A, 0)) -> Medical | J53: =INDEX(Shipments!C:C, MATCH(B53,Clean_Processing!A:A, 0)) -> 12 | K53: =INDEX(Shipments!D:D, MATCH(C53,Clean_Processing!A:A, 0)) -> 0 | L53: 44956 | M53: Delivered | N53: =IFERROR(INDEX(Shipments!G:G, MATCH(J53, Clean_Processing!C:C, 0)), "") -> 435.71256 | O53: 4324.0974 | P53: 0.90846009 | Q53: =INDEX(Products!D:D, MATCH(C53, Clean_Processing!A:A, 0)) -> 432.71 | R53: 4759.81 | S53: 3891.3874 | T53: 0.817551 | W53: South Amanda
A54: 53 | B54: 16 | C54: 45 | D54: 71 | E54: 45007 | F54: 2023 | G54: =INDEX(Products!B:B, MATCH(C54,Clean_Processing!A:A, 0)) -> And | H54: =INDEX(Suppliers!B:B, MATCH(B54, Clean_Processing!A:A, 0)) -> Freeman-Rogers | I54: =INDEX(Products!C:C, MATCH(B54,Clean_Processing!A:A, 0)) -> Clothing | J54: =INDEX(Shipments!C:C, MATCH(B54,Clean_Processing!A:A, 0)) -> 5 | K54: =INDEX(Shipments!D:D, MATCH(C54,Clean_Processing!A:A, 0)) -> Bike | L54: 44941 | M54: Delivered | N54: =IFERROR(INDEX(Shipments!G:G, MATCH(J54, Clean_Processing!C:C, 0)), "") -> 66.520284 | O54: 17356.17 | P54: 0.99618197 | Q54: =INDEX(Products!D:D, MATCH(C54, Clean_Processing!A:A, 0)) -> 245.39 | R54: 17422.69 | S54: 17110.78 | T54: 0.98209747 | W54: Lake Jaredland
A55: 54 | B55: 11 | C55: 1 | D55: 53 | E55: 44965 | F55: 2023 | G55: =INDEX(Products!B:B, MATCH(C55,Clean_Processing!A:A, 0)) -> Local | H55: =INDEX(Suppliers!B:B, MATCH(B55, Clean_Processing!A:A, 0)) -> Cross Inc | I55: =INDEX(Products!C:C, MATCH(B55,Clean_Processing!A:A, 0)) -> Furniture | J55: =INDEX(Shipments!C:C, MATCH(B55,Clean_Processing!A:A, 0)) -> 58 | K55: =INDEX(Shipments!D:D, MATCH(C55,Clean_Processing!A:A, 0)) -> Bike | L55: 45246 | M55: Delivered | N55: =IFERROR(INDEX(Shipments!G:G, MATCH(J55, Clean_Processing!C:C, 0)), "") -> 444.6528 | O55: 1682.7672 | P55: 0.79098965 | Q55: =INDEX(Products!D:D, MATCH(C55, Clean_Processing!A:A, 0)) -> 40.14 | R55: 2127.42 | S55: 1642.6272 | T55: 0.77212173 | U55: 281 | V55: Slow | W55: Lake Kevin
A56: 55 | B56: 45 | C56: 153 | D56: 61 | E56: 45157 | F56: 2023 | G56: =INDEX(Products!B:B, MATCH(C56,Clean_Processing!A:A, 0)) -> Rich | H56: =INDEX(Suppliers!B:B, MATCH(B56, Clean_Processing!A:A, 0)) -> Horton-Huffman | I56: =INDEX(Products!C:C, MATCH(B56,Clean_Processing!A:A, 0)) -> Furniture | J56: =INDEX(Shipments!C:C, MATCH(B56,Clean_Processing!A:A, 0)) -> 60 | K56: =INDEX(Shipments!D:D, MATCH(C56,Clean_Processing!A:A, 0)) -> Van | L56: 45225 | M56: Delivered | N56: =IFERROR(INDEX(Shipments!G:G, MATCH(J56, Clean_Processing!C:C, 0)), "") -> 257.20978 | O56: 7582.5102 | P56: 0.96719146 | Q56: =INDEX(Products!D:D, MATCH(C56, Clean_Processing!A:A, 0)) -> 128.52 | R56: 7839.72 | S56: 7453.9902 | T56: 0.95079802 | U56: 68 | V56: Slow | W56: Port Jeffreyton
A57: 56 | B57: 3 | C57: 60 | D57: 37 | E57: 45076 | F57: 2023 | G57: =INDEX(Products!B:B, MATCH(C57,Clean_Processing!A:A, 0)) -> Including | H57: =INDEX(Suppliers!B:B, MATCH(B57, Clean_Processing!A:A, 0)) -> Mendez-Miller | I57: =INDEX(Products!C:C, MATCH(B57,Clean_Processing!A:A, 0)) -> Food | J57: =INDEX(Shipments!C:C, MATCH(B57,Clean_Processing!A:A, 0)) -> 79 | K57: =INDEX(Shipments!D:D, MATCH(C57,Clean_Processing!A:A, 0)) -> Bike | L57: 45189 | M57: Delivered | N57: =IFERROR(INDEX(Shipments!G:G, MATCH(J57, Clean_Processing!C:C, 0)), "") -> 372.28666 | O57: 5246.9033 | P57: 0.93374727 | Q57: =INDEX(Products!D:D, MATCH(C57, Clean_Processing!A:A, 0)) -> 151.87 | R57: 5619.19 | S57: 5095.0333 | T57: 0.90672025 | U57: 113 | V57: Slow | W57: Pattonmouth
A58: 57 | B58: 19 | C58: 180 | D58: 59 | E58: 45288 | F58: 2023 | G58: =INDEX(Products!B:B, MATCH(C58,Clean_Processing!A:A, 0)) -> Eye | H58: =INDEX(Suppliers!B:B, MATCH(B58, Clean_Processing!A:A, 0)) -> King LLC | I58: =INDEX(Products!C:C, MATCH(B58,Clean_Processing!A:A, 0)) -> Electronics | J58: =INDEX(Shipments!C:C, MATCH(B58,Clean_Processing!A:A, 0)) -> 58 | K58: =INDEX(Shipments!D:D, MATCH(C58,Clean_Processing!A:A, 0)) -> Drone | L58: 45219 | M58: Delivered | N58: =IFERROR(INDEX(Shipments!G:G, MATCH(J58, Clean_Processing!C:C, 0)), "") -> 444.6528 | O58: 8763.4772 | P58: 0.95171085 | Q58: =INDEX(Products!D:D, MATCH(C58, Clean_Processing!A:A, 0)) -> 156.07 | R58: 9208.13 | S58: 8607.4072 | T58: 0.93476169 | W58: East Michael
A59: 58 | B59: 44 | C59: 60 | D59: 34 | E59: 44963 | F59: 2023 | G59: =INDEX(Products!B:B, MATCH(C59,Clean_Processing!A:A, 0)) -> Including | H59: =INDEX(Suppliers!B:B, MATCH(B59, Clean_Processing!A:A, 0)) -> Richardson Group | I59: =INDEX(Products!C:C, MATCH(B59,Clean_Processing!A:A, 0)) -> Electronics | J59: =INDEX(Shipments!C:C, MATCH(B59,Clean_Processing!A:A, 0)) -> 60 | K59: =INDEX(Shipments!D:D, MATCH(C59,Clean_Processing!A:A, 0)) -> Bike | L59: 45098 | M59: Delivered | N59: =IFERROR(INDEX(Shipments!G:G, MATCH(J59, Clean_Processing!C:C, 0)), "") -> 257.20978 | O59: 4906.3702 | P59: 0.9501877 | Q59: =INDEX(Products!D:D, MATCH(C59, Clean_Processing!A:A, 0)) -> 151.87 | R59: 5163.58 | S59: 4754.5002 | T59: 0.92077594 | U59: 135 | V59: Slow | W59: East Paulberg
A60: 59 | B60: 38 | C60: 170 | D60: 26 | E60: 45247 | F60: 2023 | G60: =INDEX(Products!B:B, MATCH(C60,Clean_Processing!A:A, 0)) -> Arm | H60: =INDEX(Suppliers!B:B, MATCH(B60, Clean_Processing!A:A, 0)) -> Gray Group | I60: =INDEX(Products!C:C, MATCH(B60,Clean_Processing!A:A, 0)) -> Furniture | J60: =INDEX(Shipments!C:C, MATCH(B60,Clean_Processing!A:A, 0)) -> 27 | K60: =INDEX(Shipments!D:D, MATCH(C60,Clean_Processing!A:A, 0)) -> 0 | L60: 44999 | M60: Delivered | N60: =IFERROR(INDEX(Shipments!G:G, MATCH(J60, Clean_Processing!C:C, 0)), "") -> 49.753309 | O60: 11200.707 | P60: 0.99557766 | Q60: =INDEX(Products!D:D, MATCH(C60, Clean_Processing!A:A, 0)) -> 432.71 | R60: 11250.46 | S60: 10767.997 | T60: 0.95711613 | W60: New Dustin
A61: 60 | B61: 8 | C61: 140 | D61: 29 | E61: 45144 | F61: 2023 | G61: =INDEX(Products!B:B, MATCH(C61,Clean_Processing!A:A, 0)) -> Information | H61: =INDEX(Suppliers!B:B, MATCH(B61, Clean_Processing!A:A, 0)) -> Andrews-Jordan | I61: =INDEX(Products!C:C, MATCH(B61,Clean_Processing!A:A, 0)) -> Medical | J61: =INDEX(Shipments!C:C, MATCH(B61,Clean_Processing!A:A, 0)) -> 27 | K61: =INDEX(Shipments!D:D, MATCH(C61,Clean_Processing!A:A, 0)) -> Bike | L61: 45128 | M61: Delivered | N61: =IFERROR(INDEX(Shipments!G:G, MATCH(J61, Clean_Processing!C:C, 0)), "") -> 49.753309 | O61: 12772.307 | P61: 0.99611971 | Q61: =INDEX(Products!D:D, MATCH(C61, Clean_Processing!A:A, 0)) -> 442.14 | R61: 12822.06 | S61: 12330.167 | T61: 0.96163695 | W61: Lake Michele
A62: 61 | B62: 10 | C62: 69 | D62: 19 | E62: 45258 | F62: 2023 | G62: =INDEX(Products!B:B, MATCH(C62,Clean_Processing!A:A, 0)) -> Without | H62: =INDEX(Suppliers!B:B, MATCH(B62, Clean_Processing!A:A, 0)) -> Wilson, Jones and Gregory | I62: =INDEX(Products!C:C, MATCH(B62,Clean_Processing!A:A, 0)) -> Medical | J62: =INDEX(Shipments!C:C, MATCH(B62,Clean_Processing!A:A, 0)) -> 4 | K62: =INDEX(Shipments!D:D, MATCH(C62,Clean_Processing!A:A, 0)) -> Drone | L62: 44995 | M62: Delivered | N62: =IFERROR(INDEX(Shipments!G:G, MATCH(J62, Clean_Processing!C:C, 0)), "") -> 183.42839 | O62: 1392.2416 | P62: 0.88358705 | Q62: =INDEX(Products!D:D, MATCH(C62, Clean_Processing!A:A, 0)) -> 82.93 | R62: 1575.67 | S62: 1309.3116 | T62: 0.83095547 | W62: Michaelmouth
A63: 62 | B63: 4 | C63: 43 | D63: 40 | E63: 44963 | F63: 2023 | G63: =INDEX(Products!B:B, MATCH(C63,Clean_Processing!A:A, 0)) -> Hope | H63: =INDEX(Suppliers!B:B, MATCH(B63, Clean_Processing!A:A, 0)) -> Martin, Dean and Glenn | I63: =INDEX(Products!C:C, MATCH(B63,Clean_Processing!A:A, 0)) -> Clothing | J63: =INDEX(Shipments!C:C, MATCH(B63,Clean_Processing!A:A, 0)) -> 27 | K63: =INDEX(Shipments!D:D, MATCH(C63,Clean_Processing!A:A, 0)) -> Bike | L63: 45006 | M63: Delivered | N63: =IFERROR(INDEX(Shipments!G:G, MATCH(J63, Clean_Processing!C:C, 0)), "") -> 49.753309 | O63: 16954.247 | P63: 0.99707402 | Q63: =INDEX(Products!D:D, MATCH(C63, Clean_Processing!A:A, 0)) -> 425.1 | R63: 17004 | S63: 16529.147 | T63: 0.97207402 | U63: 43 | V63: Slow | W63: West Anna
A64: 63 | B64: 48 | C64: 146 | D64: 37 | E64: 45231 | F64: 2023 | G64: =INDEX(Products!B:B, MATCH(C64,Clean_Processing!A:A, 0)) -> Off | H64: =INDEX(Suppliers!B:B, MATCH(B64, Clean_Processing!A:A, 0)) -> Thompson, Shaw and Brown | I64: =INDEX(Products!C:C, MATCH(B64,Clean_Processing!A:A, 0)) -> Furniture | J64: =INDEX(Shipments!C:C, MATCH(B64,Clean_Processing!A:A, 0)) -> 10 | K64: =INDEX(Shipments!D:D, MATCH(C64,Clean_Processing!A:A, 0)) -> Drone | L64: 44926 | M64: Delivered | N64: =IFERROR(INDEX(Shipments!G:G, MATCH(J64, Clean_Processing!C:C, 0)), "") -> 445.89732 | O64: 2073.4327 | P64: 0.82300956 | Q64: =INDEX(Products!D:D, MATCH(C64, Clean_Processing!A:A, 0)) -> 68.09 | R64: 2519.33 | S64: 2005.3427 | T64: 0.79598253 | W64: South Debraview
A65: 64 | B65: 8 | C65: 120 | D65: 89 | E65: 45151 | F65: 2023 | G65: =INDEX(Products!B:B, MATCH(C65,Clean_Processing!A:A, 0)) -> Seek | H65: =INDEX(Suppliers!B:B, MATCH(B65, Clean_Processing!A:A, 0)) -> Andrews-Jordan | I65: =INDEX(Products!C:C, MATCH(B65,Clean_Processing!A:A, 0)) -> Medical | J65: =INDEX(Shipments!C:C, MATCH(B65,Clean_Processing!A:A, 0)) -> 27 | K65: =INDEX(Shipments!D:D, MATCH(C65,Clean_Processing!A:A, 0)) -> Van | L65: 45173 | M65: Delivered | N65: =IFERROR(INDEX(Shipments!G:G, MATCH(J65, Clean_Processing!C:C, 0)), "") -> 49.753309 | O65: 27040.957 | P65: 0.99816345 | Q65: =INDEX(Products!D:D, MATCH(C65, Clean_Processing!A:A, 0)) -> 304.39 | R65: 27090.71 | S65: 26736.567 | T65: 0.9869275 | U65: 22 | V65: Slow | W65: Washingtonfurt
A66: 65 | B66: 45 | C66: 104 | D66: 35 | E66: 45082 | F66: 2023 | G66: =INDEX(Products!B:B, MATCH(C66,Clean_Processing!A:A, 0)) -> Program | H66: =INDEX(Suppliers!B:B, MATCH(B66, Clean_Processing!A:A, 0)) -> Horton-Huffman | I66: =INDEX(Products!C:C, MATCH(B66,Clean_Processing!A:A, 0)) -> Furniture | J66: =INDEX(Shipments!C:C, MATCH(B66,Clean_Processing!A:A, 0)) -> 60 | K66: =INDEX(Shipments!D:D, MATCH(C66,Clean_Processing!A:A, 0)) -> Drone | L66: 45178 | M66: Delivered | N66: =IFERROR(INDEX(Shipments!G:G, MATCH(J66, Clean_Processing!C:C, 0)), "") -> 257.20978 | O66: 2650.5902 | P66: 0.91154489 | Q66: =INDEX(Products!D:D, MATCH(C66, Clean_Processing!A:A, 0)) -> 83.08 | R66: 2907.8 | S66: 2567.5102 | T66: 0.88297346 | U66: 96 | V66: Slow | W66: New Carl
A67: 66 | B67: 35 | C67: 127 | D67: 57 | E67: 45183 | F67: 2023 | G67: =INDEX(Products!B:B, MATCH(C67,Clean_Processing!A:A, 0)) -> Always | H67: =INDEX(Suppliers!B:B, MATCH(B67, Clean_Processing!A:A, 0)) -> Braun-Miller | I67: =INDEX(Products!C:C, MATCH(B67,Clean_Processing!A:A, 0)) -> Food | J67: =INDEX(Shipments!C:C, MATCH(B67,Clean_Processing!A:A, 0)) -> 68 | K67: =INDEX(Shipments!D:D, MATCH(C67,Clean_Processing!A:A, 0)) -> Drone | L67: 45243 | M67: Delivered | N67: =IFERROR(INDEX(Shipments!G:G, MATCH(J67, Clean_Processing!C:C, 0)), "") -> 74.899801 | O67: 24082.84 | P67: 0.99689955 | Q67: =INDEX(Products!D:D, MATCH(C67, Clean_Processing!A:A, 0)) -> 423.82 | R67: 24157.74 | S67: 23659.02 | T67: 0.97935569 | U67: 60 | V67: Slow | W67: North Kennethbury
A68: 67 | B68: 39 | C68: 11 | D68: 56 | E68: 44968 | F68: 2023 | G68: =INDEX(Products!B:B, MATCH(C68,Clean_Processing!A:A, 0)) -> Know | H68: =INDEX(Suppliers!B:B, MATCH(B68, Clean_Processing!A:A, 0)) -> Garcia-Logan | I68: =INDEX(Products!C:C, MATCH(B68,Clean_Processing!A:A, 0)) -> Electronics | J68: =INDEX(Shipments!C:C, MATCH(B68,Clean_Processing!A:A, 0)) -> 15 | K68: =INDEX(Shipments!D:D, MATCH(C68,Clean_Processing!A:A, 0)) -> Bike | L68: 45215 | M68: Delivered | N68: =IFERROR(INDEX(Shipments!G:G, MATCH(J68, Clean_Processing!C:C, 0)), "") -> 99.677513 | O68: 26112.802 | P68: 0.99619733 | Q68: =INDEX(Products!D:D, MATCH(C68, Clean_Processing!A:A, 0)) -> 468.08 | R68: 26212.48 | S68: 25644.722 | T68: 0.97834018 | U68: 247 | V68: Slow | W68: West Christopher
A69: 68 | B69: 39 | C69: 65 | D69: 4 | E69: 45092 | F69: 2023 | G69: =INDEX(Products!B:B, MATCH(C69,Clean_Processing!A:A, 0)) -> Probably | H69: =INDEX(Suppliers!B:B, MATCH(B69, Clean_Processing!A:A, 0)) -> Garcia-Logan | I69: =INDEX(Products!C:C, MATCH(B69,Clean_Processing!A:A, 0)) -> Electronics | J69: =INDEX(Shipments!C:C, MATCH(B69,Clean_Processing!A:A, 0)) -> 15 | K69: =INDEX(Shipments!D:D, MATCH(C69,Clean_Processing!A:A, 0)) -> Truck | L69: 45268 | M69: Delivered | N69: =IFERROR(INDEX(Shipments!G:G, MATCH(J69, Clean_Processing!C:C, 0)), "") -> 99.677513 | O69: 33.522487 | P69: 0.25167032 | Q69: =INDEX(Products!D:D, MATCH(C69, Clean_Processing!A:A, 0)) -> 33.3 | R69: 133.2 | S69: 0.22248673 | T69: 0.0016703208 | U69: 176 | V69: Slow | W69: East Joshua
A70: 69 | B70: 15 | C70: 173 | D70: 74 | E70: 44973 | F70: 2023 | G70: =INDEX(Products!B:B, MATCH(C70,Clean_Processing!A:A, 0)) -> Half | H70: =INDEX(Suppliers!B:B, MATCH(B70, Clean_Processing!A:A, 0)) -> Lee, Johnston and Williams | I70: =INDEX(Products!C:C, MATCH(B70,Clean_Processing!A:A, 0)) -> Clothing | J70: =INDEX(Shipments!C:C, MATCH(B70,Clean_Processing!A:A, 0)) -> 29 | K70: =INDEX(Shipments!D:D, MATCH(C70,Clean_Processing!A:A, 0)) -> 0 | L70: 45277 | M70: Delivered | N70: =IFERROR(INDEX(Shipments!G:G, MATCH(J70, Clean_Processing!C:C, 0)), "") -> 472.4855 | O70: 28739.015 | P70: 0.98382536 | Q70: =INDEX(Products!D:D, MATCH(C70, Clean_Processing!A:A, 0)) -> 394.75 | R70: 29211.5 | S70: 28344.265 | T70: 0.97031185 | U70: 304 | V70: Slow | W70: East Jenniferbury
A71: 70 | B71: 2 | C71: 196 | D71: 87 | E71: 45227 | F71: 2023 | G71: =INDEX(Products!B:B, MATCH(C71,Clean_Processing!A:A, 0)) -> Record | H71: =INDEX(Suppliers!B:B, MATCH(B71, Clean_Processing!A:A, 0)) -> Holmes, Duncan and Reed | I71: =INDEX(Products!C:C, MATCH(B71,Clean_Processing!A:A, 0)) -> Electronics | J71: =INDEX(Shipments!C:C, MATCH(B71,Clean_Processing!A:A, 0)) -> 92 | K71: =INDEX(Shipments!D:D, MATCH(C71,Clean_Processing!A:A, 0)) -> Bike | L71: 44940 | M71: Delivered | N71: =IFERROR(INDEX(Shipments!G:G, MATCH(J71, Clean_Processing!C:C, 0)), "") -> 455.91997 | O71: 7669.01 | P71: 0.94388629 | Q71: =INDEX(Products!D:D, MATCH(C71, Clean_Processing!A:A, 0)) -> 93.39 | R71: 8124.93 | S71: 7575.62 | T71: 0.93239204 | W71: Jacobsonburgh
A72: 71 | B72: 37 | C72: 11 | D72: 98 | E72: 45064 | F72: 2023 | G72: =INDEX(Products!B:B, MATCH(C72,Clean_Processing!A:A, 0)) -> Know | H72: =INDEX(Suppliers!B:B, MATCH(B72, Clean_Processing!A:A, 0)) -> Butler Ltd | I72: =INDEX(Products!C:C, MATCH(B72,Clean_Processing!A:A, 0)) -> Electronics | J72: =INDEX(Shipments!C:C, MATCH(B72,Clean_Processing!A:A, 0)) -> 22 | K72: =INDEX(Shipments!D:D, MATCH(C72,Clean_Processing!A:A, 0)) -> Bike | L72: 45082 | M72: Delivered | N72: =IFERROR(INDEX(Shipments!G:G, MATCH(J72, Clean_Processing!C:C, 0)), "") -> 461.69547 | O72: 45410.145 | P72: 0.9899351 | Q72: =INDEX(Products!D:D, MATCH(C72, Clean_Processing!A:A, 0)) -> 468.08 | R72: 45871.84 | S72: 44942.065 | T72: 0.97973102 | U72: 18 | V72: Slow | W72: Geraldburgh
A73: 72 | B73: 31 | C73: 133 | D73: 84 | E73: 45016 | F73: 2023 | G73: =INDEX(Products!B:B, MATCH(C73,Clean_Processing!A:A, 0)) -> Again | H73: =INDEX(Suppliers!B:B, MATCH(B73, Clean_Processing!A:A, 0)) -> Turner LLC | I73: =INDEX(Products!C:C, MATCH(B73,Clean_Processing!A:A, 0)) -> Food | J73: =INDEX(Shipments!C:C, MATCH(B73,Clean_Processing!A:A, 0)) -> 36 | K73: =INDEX(Shipments!D:D, MATCH(C73,Clean_Processing!A:A, 0)) -> Drone | L73: 45230 | M73: Delivered | N73: =IFERROR(INDEX(Shipments!G:G, MATCH(J73, Clean_Processing!C:C, 0)), "") -> 177.62958 | O73: 26733.45 | P73: 0.99339939 | Q73: =INDEX(Products!D:D, MATCH(C73, Clean_Processing!A:A, 0)) -> 320.37 | R73: 26911.08 | S73: 26413.08 | T73: 0.98149463 | U73: 214 | V73: Slow | W73: East Danielletown
A74: 73 | B74: 18 | C74: 47 | D74: 75 | E74: 45153 | F74: 2023 | G74: =INDEX(Products!B:B, MATCH(C74,Clean_Processing!A:A, 0)) -> Sister | H74: =INDEX(Suppliers!B:B, MATCH(B74, Clean_Processing!A:A, 0)) -> Walsh and Sons | I74: =INDEX(Products!C:C, MATCH(B74,Clean_Processing!A:A, 0)) -> Medical | J74: =INDEX(Shipments!C:C, MATCH(B74,Clean_Processing!A:A, 0)) -> 7 | K74: =INDEX(Shipments!D:D, MATCH(C74,Clean_Processing!A:A, 0)) -> Bike | L74: 45005 | M74: Delivered | N74: =IFERROR(INDEX(Shipments!G:G, MATCH(J74, Clean_Processing!C:C, 0)), "") -> 277.62922 | O74: 14985.621 | P74: 0.98181061 | Q74: =INDEX(Products!D:D, MATCH(C74, Clean_Processing!A:A, 0)) -> 203.51 | R74: 15263.25 | S74: 14782.111 | T74: 0.96847728 | W74: Martinezberg
A75: 74 | B75: 41 | C75: 126 | D75: 12 | E75: 45150 | F75: 2023 | G75: =INDEX(Products!B:B, MATCH(C75,Clean_Processing!A:A, 0)) -> Article | H75: =INDEX(Suppliers!B:B, MATCH(B75, Clean_Processing!A:A, 0)) -> Gomez and Sons | I75: =INDEX(Products!C:C, MATCH(B75,Clean_Processing!A:A, 0)) -> Food | J75: =INDEX(Shipments!C:C, MATCH(B75,Clean_Processing!A:A, 0)) -> 28 | K75: =INDEX(Shipments!D:D, MATCH(C75,Clean_Processing!A:A, 0)) -> Bike | L75: 45164 | M75: Delivered | N75: =IFERROR(INDEX(Shipments!G:G, MATCH(J75, Clean_Processing!C:C, 0)), "") -> 362.48678 | O75: 5075.1932 | P75: 0.93333797 | Q75: =INDEX(Products!D:D, MATCH(C75, Clean_Processing!A:A, 0)) -> 453.14 | R75: 5437.68 | S75: 4622.0532 | T75: 0.85000464 | U75: 14 | V75: Normal | W75: East Stephanieburgh
A76: 75 | B76: 23 | C76: 105 | D76: 43 | E76: 45167 | F76: 2023 | G76: =INDEX(Products!B:B, MATCH(C76,Clean_Processing!A:A, 0)) -> Herself | H76: =INDEX(Suppliers!B:B, MATCH(B76, Clean_Processing!A:A, 0)) -> Thompson, West and Weaver | I76: =INDEX(Products!C:C, MATCH(B76,Clean_Processing!A:A, 0)) -> Furniture | J76: =INDEX(Shipments!C:C, MATCH(B76,Clean_Processing!A:A, 0)) -> 55 | K76: =INDEX(Shipments!D:D, MATCH(C76,Clean_Processing!A:A, 0)) -> 0 | L76: 45114 | M76: Delivered | N76: =IFERROR(INDEX(Shipments!G:G, MATCH(J76, Clean_Processing!C:C, 0)), "") -> 319.11105 | O76: 17641.989 | P76: 0.98223321 | Q76: =INDEX(Products!D:D, MATCH(C76, Clean_Processing!A:A, 0)) -> 417.7 | R76: 17961.1 | S76: 17224.289 | T76: 0.9589774 | W76: Banksstad
A77: 76 | B77: 43 | C77: 27 | D77: 21 | E77: 45091 | F77: 2023 | G77: =INDEX(Products!B:B, MATCH(C77,Clean_Processing!A:A, 0)) -> Child | H77: =INDEX(Suppliers!B:B, MATCH(B77, Clean_Processing!A:A, 0)) -> Johnson, Knight and Dawson | I77: =INDEX(Products!C:C, MATCH(B77,Clean_Processing!A:A, 0)) -> Food | J77: =INDEX(Shipments!C:C, MATCH(B77,Clean_Processing!A:A, 0)) -> 3 | K77: =INDEX(Shipments!D:D, MATCH(C77,Clean_Processing!A:A, 0)) -> Truck | L77: 45097 | M77: Delivered | N77: =IFERROR(INDEX(Shipments!G:G, MATCH(J77, Clean_Processing!C:C, 0)), "") -> 254.79639 | O77: 8807.3336 | P77: 0.97188339 | Q77: =INDEX(Products!D:D, MATCH(C77, Clean_Processing!A:A, 0)) -> 431.53 | R77: 9062.13 | S77: 8375.8036 | T77: 0.92426434 | U77: 6 | V77: Fast | W77: Lake Sharon
A78: 77 | B78: 27 | C78: 178 | D78: 64 | E78: 45095 | F78: 2023 | G78: =INDEX(Products!B:B, MATCH(C78,Clean_Processing!A:A, 0)) -> Magazine | H78: =INDEX(Suppliers!B:B, MATCH(B78, Clean_Processing!A:A, 0)) -> Wheeler, Fleming and Sherman | I78: =INDEX(Products!C:C, MATCH(B78,Clean_Processing!A:A, 0)) -> Food | J78: =INDEX(Shipments!C:C, MATCH(B78,Clean_Processing!A:A, 0)) -> 32 | K78: =INDEX(Shipments!D:D, MATCH(C78,Clean_Processing!A:A, 0)) -> Bike | L78: 45172 | M78: Delivered | N78: =IFERROR(INDEX(Shipments!G:G, MATCH(J78, Clean_Processing!C:C, 0)), "") -> 173.69079 | O78: 26015.749 | P78: 0.99336791 | Q78: =INDEX(Products!D:D, MATCH(C78, Clean_Processing!A:A, 0)) -> 409.21 | R78: 26189.44 | S78: 25606.539 | T78: 0.97774291 | U78: 77 | V78: Slow | W78: Port Lisa
A79: 78 | B79: 43 | C79: 103 | D79: 98 | E79: 45074 | F79: 2023 | G79: =INDEX(Products!B:B, MATCH(C79,Clean_Processing!A:A, 0)) -> Scientist | H79: =INDEX(Suppliers!B:B, MATCH(B79, Clean_Processing!A:A, 0)) -> Johnson, Knight and Dawson | I79: =INDEX(Products!C:C, MATCH(B79,Clean_Processing!A:A, 0)) -> Food | J79: =INDEX(Shipments!C:C, MATCH(B79,Clean_Processing!A:A, 0)) -> 3 | K79: =INDEX(Shipments!D:D, MATCH(C79,Clean_Processing!A:A, 0)) -> Drone | L79: 45136 | M79: Delivered | N79: =IFERROR(INDEX(Shipments!G:G, MATCH(J79, Clean_Processing!C:C, 0)), "") -> 254.79639 | O79: 18161.364 | P79: 0.98616452 | Q79: =INDEX(Products!D:D, MATCH(C79, Clean_Processing!A:A, 0)) -> 187.92 | R79: 18416.16 | S79: 17973.444 | T79: 0.97596044 | U79: 62 | V79: Slow | W79: Roseburgh
A80: 79 | B80: 3 | C80: 117 | D80: 12 | E80: 45208 | F80: 2023 | G80: =INDEX(Products!B:B, MATCH(C80,Clean_Processing!A:A, 0)) -> Girl | H80: =INDEX(Suppliers!B:B, MATCH(B80, Clean_Processing!A:A, 0)) -> Mendez-Miller | I80: =INDEX(Products!C:C, MATCH(B80,Clean_Processing!A:A, 0)) -> Food | J80: =INDEX(Shipments!C:C, MATCH(B80,Clean_Processing!A:A, 0)) -> 79 | K80: =INDEX(Shipments!D:D, MATCH(C80,Clean_Processing!A:A, 0)) -> Truck | L80: 45098 | M80: Delivered | N80: =IFERROR(INDEX(Shipments!G:G, MATCH(J80, Clean_Processing!C:C, 0)), "") -> 372.28666 | O80: 323.47334 | P80: 0.46492087 | Q80: =INDEX(Products!D:D, MATCH(C80, Clean_Processing!A:A, 0)) -> 57.98 | R80: 695.76 | S80: 265.49334 | T80: 0.38158754 | W80: North Don
A81: 80 | B81: 17 | C81: 83 | D81: 15 | E81: 45088 | F81: 2023 | G81: =INDEX(Products!B:B, MATCH(C81,Clean_Processing!A:A, 0)) -> Resource | H81: =INDEX(Suppliers!B:B, MATCH(B81, Clean_Processing!A:A, 0)) -> Acevedo PLC | I81: =INDEX(Products!C:C, MATCH(B81,Clean_Processing!A:A, 0)) -> Medical | J81: =INDEX(Shipments!C:C, MATCH(B81,Clean_Processing!A:A, 0)) -> 12 | K81: =INDEX(Shipments!D:D, MATCH(C81,Clean_Processing!A:A, 0)) -> Bike | L81: 45180 | M81: Delivered | N81: =IFERROR(INDEX(Shipments!G:G, MATCH(J81, Clean_Processing!C:C, 0)), "") -> 435.71256 | O81: 3520.9874 | P81: 0.88987981 | Q81: =INDEX(Products!D:D, MATCH(C81, Clean_Processing!A:A, 0)) -> 263.78 | R81: 3956.7 | S81: 3257.2074 | T81: 0.82321314 | U81: 92 | V81: Slow | W81: Moralesburgh
A82: 81 | B82: 33 | C82: 1 | D82: 85 | E82: 45133 | F82: 2023 | G82: =INDEX(Products!B:B, MATCH(C82,Clean_Processing!A:A, 0)) -> Local | H82: =INDEX(Suppliers!B:B, MATCH(B82, Clean_Processing!A:A, 0)) -> Andrews-Hubbard | I82: =INDEX(Products!C:C, MATCH(B82,Clean_Processing!A:A, 0)) -> Clothing | J82: =INDEX(Shipments!C:C, MATCH(B82,Clean_Processing!A:A, 0)) -> 9 | K82: =INDEX(Shipments!D:D, MATCH(C82,Clean_Processing!A:A, 0)) -> Bike | L82: 45048 | M82: Delivered | N82: =IFERROR(INDEX(Shipments!G:G, MATCH(J82, Clean_Processing!C:C, 0)), "") -> 398.406 | O82: 3013.494 | P82: 0.88323046 | Q82: =INDEX(Products!D:D, MATCH(C82, Clean_Processing!A:A, 0)) -> 40.14 | R82: 3411.9 | S82: 2973.354 | T82: 0.87146575 | W82: Georgetown
A83: 82 | B83: 30 | C83: 106 | D83: 7 | E83: 45204 | F83: 2023 | G83: =INDEX(Products!B:B, MATCH(C83,Clean_Processing!A:A, 0)) -> Sea | H83: =INDEX(Suppliers!B:B, MATCH(B83, Clean_Processing!A:A, 0)) -> Burton-Logan | I83: =INDEX(Products!C:C, MATCH(B83,Clean_Processing!A:A, 0)) -> Furniture | J83: =INDEX(Shipments!C:C, MATCH(B83,Clean_Processing!A:A, 0)) -> 17 | K83: =INDEX(Shipments!D:D, MATCH(C83,Clean_Processing!A:A, 0)) -> 0 | L83: 45011 | M83: Delivered | N83: =IFERROR(INDEX(Shipments!G:G, MATCH(J83, Clean_Processing!C:C, 0)), "") -> 480.10591 | O83: 1992.6441 | P83: 0.80584131 | Q83: =INDEX(Products!D:D, MATCH(C83, Clean_Processing!A:A, 0)) -> 353.25 | R83: 2472.75 | S83: 1639.3941 | T83: 0.66298416 | W83: South Donaldfort
A84: 83 | B84: 34 | C84: 93 | D84: 80 | E84: 45023 | F84: 2023 | G84: =INDEX(Products!B:B, MATCH(C84,Clean_Processing!A:A, 0)) -> Local | H84: =INDEX(Suppliers!B:B, MATCH(B84, Clean_Processing!A:A, 0)) -> Singh Ltd | I84: =INDEX(Products!C:C, MATCH(B84,Clean_Processing!A:A, 0)) -> Clothing | J84: =INDEX(Shipments!C:C, MATCH(B84,Clean_Processing!A:A, 0)) -> 68 | K84: =INDEX(Shipments!D:D, MATCH(C84,Clean_Processing!A:A, 0)) -> Bike | L84: 44977 | M84: Delivered | N84: =IFERROR(INDEX(Shipments!G:G, MATCH(J84, Clean_Processing!C:C, 0)), "") -> 74.899801 | O84: 3197.9002 | P84: 0.97711446 | Q84: =INDEX(Products!D:D, MATCH(C84, Clean_Processing!A:A, 0)) -> 40.91 | R84: 3272.8 | S84: 3156.9902 | T84: 0.96461446 | W84: Chambershaven
A85: 84 | B85: 41 | C85: 114 | D85: 98 | E85: 45182 | F85: 2023 | G85: =INDEX(Products!B:B, MATCH(C85,Clean_Processing!A:A, 0)) -> Natural | H85: =INDEX(Suppliers!B:B, MATCH(B85, Clean_Processing!A:A, 0)) -> Gomez and Sons | I85: =INDEX(Products!C:C, MATCH(B85,Clean_Processing!A:A, 0)) -> Food | J85: =INDEX(Shipments!C:C, MATCH(B85,Clean_Processing!A:A, 0)) -> 28 | K85: =INDEX(Shipments!D:D, MATCH(C85,Clean_Processing!A:A, 0)) -> Van | L85: 45205 | M85: Delivered | N85: =IFERROR(INDEX(Shipments!G:G, MATCH(J85, Clean_Processing!C:C, 0)), "") -> 362.48678 | O85: 45674.973 | P85: 0.99212626 | Q85: =INDEX(Products!D:D, MATCH(C85, Clean_Processing!A:A, 0)) -> 469.77 | R85: 46037.46 | S85: 45205.203 | T85: 0.98192218 | U85: 23 | V85: Slow | W85: Abbottborough
A86: 85 | B86: 14 | C86: 69 | D86: 71 | E86: 44953 | F86: 2023 | G86: =INDEX(Products!B:B, MATCH(C86,Clean_Processing!A:A, 0)) -> Without | H86: =INDEX(Suppliers!B:B, MATCH(B86, Clean_Processing!A:A, 0)) -> Walsh-Perez | I86: =INDEX(Products!C:C, MATCH(B86,Clean_Processing!A:A, 0)) -> Electronics | J86: =INDEX(Shipments!C:C, MATCH(B86,Clean_Processing!A:A, 0)) -> 35 | K86: =INDEX(Shipments!D:D, MATCH(C86,Clean_Processing!A:A, 0)) -> Drone | L86: 45258 | M86: Delivered | N86: =IFERROR(INDEX(Shipments!G:G, MATCH(J86, Clean_Processing!C:C, 0)), "") -> 330.20981 | O86: 5557.8202 | P86: 0.94391846 | Q86: =INDEX(Products!D:D, MATCH(C86, Clean_Processing!A:A, 0)) -> 82.93 | R86: 5888.03 | S86: 5474.8902 | T86: 0.92983395 | U86: 305 | V86: Slow | W86: Andreaberg
A87: 86 | B87: 19 | C87: 113 | D87: 90 | E87: 44994 | F87: 2023 | G87: =INDEX(Products!B:B, MATCH(C87,Clean_Processing!A:A, 0)) -> Right | H87: =INDEX(Suppliers!B:B, MATCH(B87, Clean_Processing!A:A, 0)) -> King LLC | I87: =INDEX(Products!C:C, MATCH(B87,Clean_Processing!A:A, 0)) -> Electronics | J87: =INDEX(Shipments!C:C, MATCH(B87,Clean_Processing!A:A, 0)) -> 58 | K87: =INDEX(Shipments!D:D, MATCH(C87,Clean_Processing!A:A, 0)) -> Truck | L87: 45016 | M87: Delivered | N87: =IFERROR(INDEX(Shipments!G:G, MATCH(J87, Clean_Processing!C:C, 0)), "") -> 444.6528 | O87: 29559.547 | P87: 0.98518031 | Q87: =INDEX(Products!D:D, MATCH(C87, Clean_Processing!A:A, 0)) -> 333.38 | R87: 30004.2 | S87: 29226.167 | T87: 0.9740692 | U87: 22 | V87: Slow | W87: North Aliciabury
A88: 87 | B88: 8 | C88: 8 | D88: 81 | E88: 45175 | F88: 2023 | G88: =INDEX(Products!B:B, MATCH(C88,Clean_Processing!A:A, 0)) -> Science | H88: =INDEX(Suppliers!B:B, MATCH(B88, Clean_Processing!A:A, 0)) -> Andrews-Jordan | I88: =INDEX(Products!C:C, MATCH(B88,Clean_Processing!A:A, 0)) -> Medical | J88: =INDEX(Shipments!C:C, MATCH(B88,Clean_Processing!A:A, 0)) -> 27 | K88: =INDEX(Shipments!D:D, MATCH(C88,Clean_Processing!A:A, 0)) -> Drone | L88: 45279 | M88: Delivered | N88: =IFERROR(INDEX(Shipments!G:G, MATCH(J88, Clean_Processing!C:C, 0)), "") -> 49.753309 | O88: 27177.587 | P88: 0.99817267 | Q88: =INDEX(Products!D:D, MATCH(C88, Clean_Processing!A:A, 0)) -> 336.14 | R88: 27227.34 | S88: 26841.447 | T88: 0.98582699 | U88: 104 | V88: Slow | W88: Stevenstad
A89: 88 | B89: 16 | C89: 182 | D89: 21 | E89: 45238 | F89: 2023 | G89: =INDEX(Products!B:B, MATCH(C89,Clean_Processing!A:A, 0)) -> Language | H89: =INDEX(Suppliers!B:B, MATCH(B89, Clean_Processing!A:A, 0)) -> Freeman-Rogers | I89: =INDEX(Products!C:C, MATCH(B89,Clean_Processing!A:A, 0)) -> Clothing | J89: =INDEX(Shipments!C:C, MATCH(B89,Clean_Processing!A:A, 0)) -> 5 | K89: =INDEX(Shipments!D:D, MATCH(C89,Clean_Processing!A:A, 0)) -> 0 | L89: 45012 | M89: Delivered | N89: =IFERROR(INDEX(Shipments!G:G, MATCH(J89, Clean_Processing!C:C, 0)), "") -> 66.520284 | O89: 2404.3397 | P89: 0.97307808 | Q89: =INDEX(Products!D:D, MATCH(C89, Clean_Processing!A:A, 0)) -> 117.66 | R89: 2470.86 | S89: 2286.6797 | T89: 0.92545904 | W89: Christinaville
A90: 89 | B90: 36 | C90: 4 | D90: 71 | E90: 45086 | F90: 2023 | G90: =INDEX(Products!B:B, MATCH(C90,Clean_Processing!A:A, 0)) -> Step | H90: =INDEX(Suppliers!B:B, MATCH(B90, Clean_Processing!A:A, 0)) -> Petersen Inc | I90: =INDEX(Products!C:C, MATCH(B90,Clean_Processing!A:A, 0)) -> Electronics | J90: =INDEX(Shipments!C:C, MATCH(B90,Clean_Processing!A:A, 0)) -> 74 | K90: =INDEX(Shipments!D:D, MATCH(C90,Clean_Processing!A:A, 0)) -> Drone | L90: 44968 | M90: Delivered | N90: =IFERROR(INDEX(Shipments!G:G, MATCH(J90, Clean_Processing!C:C, 0)), "") -> 131.6184 | O90: 32044.162 | P90: 0.9959094 | Q90: =INDEX(Products!D:D, MATCH(C90, Clean_Processing!A:A, 0)) -> 453.18 | R90: 32175.78 | S90: 31590.982 | T90: 0.98182489 | W90: Lake Jill
A91: 90 | B91: 6 | C91: 58 | D91: 15 | E91: 45135 | F91: 2023 | G91: =INDEX(Products!B:B, MATCH(C91,Clean_Processing!A:A, 0)) -> Even | H91: =INDEX(Suppliers!B:B, MATCH(B91, Clean_Processing!A:A, 0)) -> Dunn Ltd | I91: =INDEX(Products!C:C, MATCH(B91,Clean_Processing!A:A, 0)) -> Clothing | J91: =INDEX(Shipments!C:C, MATCH(B91,Clean_Processing!A:A, 0)) -> 57 | K91: =INDEX(Shipments!D:D, MATCH(C91,Clean_Processing!A:A, 0)) -> Van | L91: 45129 | M91: Delivered | N91: =IFERROR(INDEX(Shipments!G:G, MATCH(J91, Clean_Processing!C:C, 0)), "") -> 68.653463 | O91: 5340.4965 | P91: 0.9873079 | Q91: =INDEX(Products!D:D, MATCH(C91, Clean_Processing!A:A, 0)) -> 360.61 | R91: 5409.15 | S91: 4979.8865 | T91: 0.92064124 | W91: Port Michaelville
A92: 91 | B92: 8 | C92: 166 | D92: 20 | E92: 45163 | F92: 2023 | G92: =INDEX(Products!B:B, MATCH(C92,Clean_Processing!A:A, 0)) -> Good | H92: =INDEX(Suppliers!B:B, MATCH(B92, Clean_Processing!A:A, 0)) -> Andrews-Jordan | I92: =INDEX(Products!C:C, MATCH(B92,Clean_Processing!A:A, 0)) -> Medical | J92: =INDEX(Shipments!C:C, MATCH(B92,Clean_Processing!A:A, 0)) -> 27 | K92: =INDEX(Shipments!D:D, MATCH(C92,Clean_Processing!A:A, 0)) -> Bike | L92: 45245 | M92: Delivered | N92: =IFERROR(INDEX(Shipments!G:G, MATCH(J92, Clean_Processing!C:C, 0)), "") -> 49.753309 | O92: 7342.2467 | P92: 0.9932693 | Q92: =INDEX(Products!D:D, MATCH(C92, Clean_Processing!A:A, 0)) -> 369.6 | R92: 7392 | S92: 6972.6467 | T92: 0.9432693 | U92: 82 | V92: Slow | W92: East Kimberlyport
A93: 92 | B93: 46 | C93: 75 | D93: 66 | E93: 45182 | F93: 2023 | G93: =INDEX(Products!B:B, MATCH(C93,Clean_Processing!A:A, 0)) -> People | H93: =INDEX(Suppliers!B:B, MATCH(B93, Clean_Processing!A:A, 0)) -> Bailey PLC | I93: =INDEX(Products!C:C, MATCH(B93,Clean_Processing!A:A, 0)) -> Medical | J93: =INDEX(Shipments!C:C, MATCH(B93,Clean_Processing!A:A, 0)) -> 19 | K93: =INDEX(Shipments!D:D, MATCH(C93,Clean_Processing!A:A, 0)) -> Drone | L93: 44962 | M93: Delivered | N93: =IFERROR(INDEX(Shipments!G:G, MATCH(J93, Clean_Processing!C:C, 0)), "") -> 194.0078 | O93: 7820.3722 | P93: 0.97579254 | Q93: =INDEX(Products!D:D, MATCH(C93, Clean_Processing!A:A, 0)) -> 121.43 | R93: 8014.38 | S93: 7698.9422 | T93: 0.96064102 | W93: Port Toddville
A94: 93 | B94: 18 | C94: 107 | D94: 62 | E94: 45288 | F94: 2023 | G94: =INDEX(Products!B:B, MATCH(C94,Clean_Processing!A:A, 0)) -> Billion | H94: =INDEX(Suppliers!B:B, MATCH(B94, Clean_Processing!A:A, 0)) -> Walsh and Sons | I94: =INDEX(Products!C:C, MATCH(B94,Clean_Processing!A:A, 0)) -> Medical | J94: =INDEX(Shipments!C:C, MATCH(B94,Clean_Processing!A:A, 0)) -> 7 | K94: =INDEX(Shipments!D:D, MATCH(C94,Clean_Processing!A:A, 0)) -> 0 | L94: 45259 | M94: Delivered | N94: =IFERROR(INDEX(Shipments!G:G, MATCH(J94, Clean_Processing!C:C, 0)), "") -> 277.62922 | O94: 18804.731 | P94: 0.985451 | Q94: =INDEX(Products!D:D, MATCH(C94, Clean_Processing!A:A, 0)) -> 307.78 | R94: 19082.36 | S94: 18496.951 | T94: 0.96932197 | W94: Roberttown
A95: 94 | B95: 16 | C95: 117 | D95: 71 | E95: 45168 | F95: 2023 | G95: =INDEX(Products!B:B, MATCH(C95,Clean_Processing!A:A, 0)) -> Girl | H95: =INDEX(Suppliers!B:B, MATCH(B95, Clean_Processing!A:A, 0)) -> Freeman-Rogers | I95: =INDEX(Products!C:C, MATCH(B95,Clean_Processing!A:A, 0)) -> Clothing | J95: =INDEX(Shipments!C:C, MATCH(B95,Clean_Processing!A:A, 0)) -> 5 | K95: =INDEX(Shipments!D:D, MATCH(C95,Clean_Processing!A:A, 0)) -> Truck | L95: 45280 | M95: Delivered | N95: =IFERROR(INDEX(Shipments!G:G, MATCH(J95, Clean_Processing!C:C, 0)), "") -> 66.520284 | O95: 4050.0597 | P95: 0.98384089 | Q95: =INDEX(Products!D:D, MATCH(C95, Clean_Processing!A:A, 0)) -> 57.98 | R95: 4116.58 | S95: 3992.0797 | T95: 0.96975638 | U95: 112 | V95: Slow | W95: Margaretstad
A96: 95 | B96: 25 | C96: 49 | D96: 77 | E96: 45001 | F96: 2023 | G96: =INDEX(Products!B:B, MATCH(C96,Clean_Processing!A:A, 0)) -> Ability | H96: =INDEX(Suppliers!B:B, MATCH(B96, Clean_Processing!A:A, 0)) -> Kim-Cole | I96: =INDEX(Products!C:C, MATCH(B96,Clean_Processing!A:A, 0)) -> Furniture | J96: =INDEX(Shipments!C:C, MATCH(B96,Clean_Processing!A:A, 0)) -> 35 | K96: =INDEX(Shipments!D:D, MATCH(C96,Clean_Processing!A:A, 0)) -> Drone | L96: 45012 | M96: Delivered | N96: =IFERROR(INDEX(Shipments!G:G, MATCH(J96, Clean_Processing!C:C, 0)), "") -> 330.20981 | O96: 14499.22 | P96: 0.9777328 | Q96: =INDEX(Products!D:D, MATCH(C96, Clean_Processing!A:A, 0)) -> 192.59 | R96: 14829.43 | S96: 14306.63 | T96: 0.96474579 | U96: 11 | V96: Normal | W96: West Lisa
A97: 96 | B97: 48 | C97: 35 | D97: 9 | E97: 45187 | F97: 2023 | G97: =INDEX(Products!B:B, MATCH(C97,Clean_Processing!A:A, 0)) -> State | H97: =INDEX(Suppliers!B:B, MATCH(B97, Clean_Processing!A:A, 0)) -> Thompson, Shaw and Brown | I97: =INDEX(Products!C:C, MATCH(B97,Clean_Processing!A:A, 0)) -> Furniture | J97: =INDEX(Shipments!C:C, MATCH(B97,Clean_Processing!A:A, 0)) -> 10 | K97: =INDEX(Shipments!D:D, MATCH(C97,Clean_Processing!A:A, 0)) -> Drone | L97: 45084 | M97: Delivered | N97: =IFERROR(INDEX(Shipments!G:G, MATCH(J97, Clean_Processing!C:C, 0)), "") -> 445.89732 | O97: 1573.2527 | P97: 0.77916583 | Q97: =INDEX(Products!D:D, MATCH(C97, Clean_Processing!A:A, 0)) -> 224.35 | R97: 2019.15 | S97: 1348.9027 | T97: 0.66805472 | W97: North Davidtown
A98: 97 | B98: 50 | C98: 107 | D98: 44 | E98: 45068 | F98: 2023 | G98: =INDEX(Products!B:B, MATCH(C98,Clean_Processing!A:A, 0)) -> Billion | H98: =INDEX(Suppliers!B:B, MATCH(B98, Clean_Processing!A:A, 0)) -> Waters-Robinson | I98: =INDEX(Products!C:C, MATCH(B98,Clean_Processing!A:A, 0)) -> Medical | J98: =INDEX(Shipments!C:C, MATCH(B98,Clean_Processing!A:A, 0)) -> 9 | K98: =INDEX(Shipments!D:D, MATCH(C98,Clean_Processing!A:A, 0)) -> 0 | L98: 45048 | M98: Delivered | N98: =IFERROR(INDEX(Shipments!G:G, MATCH(J98, Clean_Processing!C:C, 0)), "") -> 398.406 | O98: 13143.914 | P98: 0.97058067 | Q98: =INDEX(Products!D:D, MATCH(C98, Clean_Processing!A:A, 0)) -> 307.78 | R98: 13542.32 | S98: 12836.134 | T98: 0.9478534 | W98: Veronicaview
A99: 98 | B99: 18 | C99: 1 | D99: 37 | E99: 45186 | F99: 2023 | G99: =INDEX(Products!B:B, MATCH(C99,Clean_Processing!A:A, 0)) -> Local | H99: =INDEX(Suppliers!B:B, MATCH(B99, Clean_Processing!A:A, 0)) -> Walsh and Sons | I99: =INDEX(Products!C:C, MATCH(B99,Clean_Processing!A:A, 0)) -> Medical | J99: =INDEX(Shipments!C:C, MATCH(B99,Clean_Processing!A:A, 0)) -> 7 | K99: =INDEX(Shipments!D:D, MATCH(C99,Clean_Processing!A:A, 0)) -> Bike | L99: 45163 | M99: Delivered | N99: =IFERROR(INDEX(Shipments!G:G, MATCH(J99, Clean_Processing!C:C, 0)), "") -> 277.62922 | O99: 1207.5508 | P99: 0.81306695 | Q99: =INDEX(Products!D:D, MATCH(C99, Clean_Processing!A:A, 0)) -> 40.14 | R99: 1485.18 | S99: 1167.4108 | T99: 0.78603993 | W99: Rebeccaland
A100: 99 | B100: 38 | C100: 149 | D100: 85 | E100: 45079 | F100: 2023 | G100: =INDEX(Products!B:B, MATCH(C100,Clean_Processing!A:A, 0)) -> Subject | H100: =INDEX(Suppliers!B:B, MATCH(B100, Clean_Processing!A:A, 0)) -> Gray Group | I100: =INDEX(Products!C:C, MATCH(B100,Clean_Processing!A:A, 0)) -> Furniture | J100: =INDEX(Shipments!C:C, MATCH(B100,Clean_Processing!A:A, 0)) -> 27 | K100: =INDEX(Shipments!D:D, MATCH(C100,Clean_Processing!A:A, 0)) -> 0 | L100: 44960 | M100: Delivered | N100: =IFERROR(INDEX(Shipments!G:G, MATCH(J100, Clean_Processing!C:C, 0)), "") -> 49.753309 | O100: 33872.047 | P100: 0.99853329 | Q100: =INDEX(Products!D:D, MATCH(C100, Clean_Processing!A:A, 0)) -> 399.08 | R100: 33921.8 | S100: 33472.967 | T100: 0.98676859 | W100: Susanborough
...

Sheet Products
A1: product_id | B1: product_name | C1: category | D1: unit_price
A2: 1 | B2: Local | C2: Electronics | D2: 40.14
A3: 2 | B3: Receive | C3: Electronics | D3: 317.4
A4: 3 | B4: Near | C4: Food | D4: 118.33
A5: 4 | B5: Step | C5: Clothing | D5: 453.18
A6: 5 | B6: Stage | C6: Clothing | D6: 430.52
A7: 6 | B7: Year | C7: Clothing | D7: 40.07
A8: 7 | B8: Last | C8: Electronics | D8: 122.81
A9: 8 | B9: Science | C9: Medical | D9: 336.14
A10: 9 | B10: Fill | C10: Electronics | D10: 111.05
A11: 10 | B11: Sport | C11: Medical | D11: 70.49
A12: 11 | B12: Know | C12: Furniture | D12: 468.08
A13: 12 | B13: Small | C13: Electronics | D13: 287.67
... A201: 200 | B201: Pressure | C201: Electronics | D201: 220.11

Sheet Shipments
A1: shipment_id | B1: order_id | C1: vehicle_id | D1: Vehicle_type | E1: scheduled_delivery | F1: actual_delivery | G1: delivery_cost
A2: 1 | B2: 3655 | C2: 28 | D2: =INDEX(Vehicles!B:B, MATCH(C2, Shipments!C:C, 0)) -> Bike | E2: 45045 | F2: 45044 | G2: 425.16828
A3: 2 | B3: 3347 | C3: 92 | D3: =INDEX(Vehicles!B:B, MATCH(C3, Shipments!C:C, 0)) -> Drone | E3: 45154 | F3: 45156 | G3: 83.688912
A4: 3 | B4: 3150 | C4: 79 | D4: =INDEX(Vehicles!B:B, MATCH(C4, Shipments!C:C, 0)) -> Truck | E4: 45121 | F4: 45120 | G4: 275.21966
A5: 4 | B5: 2226 | C5: 27 | D5: =INDEX(Vehicles!B:B, MATCH(C5, Shipments!C:C, 0)) -> Drone | E5: 45271 | F5: 45273 | G5: 223.95864
A6: 5 | B6: 4293 | C6: 44 | D6: =INDEX(Vehicles!B:B, MATCH(C6, Shipments!C:C, 0)) -> Van | E6: 45091 | F6: 45090 | G6: 254.52575
A7: 6 | B7: 3178 | C7: 57 | D7: =INDEX(Vehicles!B:B, MATCH(C7, Shipments!C:C, 0)) -> Bike | E7: 45237 | F7: 45237 | G7: 192.75092
A8: 7 | B8: 634 | C8: 77 | D8: =INDEX(Vehicles!B:B, MATCH(C8, Shipments!C:C, 0)) -> Truck | E8: 45284 | F8: 45286 | G8: 92.50701
A9: 8 | B9: 3310 | C9: 27 | D9: =INDEX(Vehicles!B:B, MATCH(C9, Shipments!C:C, 0)) -> Drone | E9: 45038 | F9: 45039 | G9: 183.10009
A10: 9 | B10: 2246 | C10: 32 | D10: =INDEX(Vehicles!B:B, MATCH(C10, Shipments!C:C, 0)) -> Truck | E10: 45075 | F10: 45075 | G10: 195.92759
A11: 10 | B11: 3848 | C11: 4 | D11: =INDEX(Vehicles!B:B, MATCH(C11, Shipments!C:C, 0)) -> Van | E11: 45278 | F11: 45281 | G11: 129.59572
A12: 11 | B12: 530 | C12: 58 | D12: =INDEX(Vehicles!B:B, MATCH(C12, Shipments!C:C, 0)) -> Bike | E12: 45292 | F12: 45291 | G12: 200.54624
A13: 12 | B13: 2828 | C13: 47 | D13: =INDEX(Vehicles!B:B, MATCH(C13, Shipments!C:C, 0)) -> Drone | E13: 45122 | F13: 45121 | G13: 250.56916
... A4001: 4000 | B4001: 1025 | C4001: 96 | D4001: =INDEX(Vehicles!B:B, MATCH(C4001, Shipments!C:C, 0)) -> 0 | E4001: 45126 | F4001: 45127 | G4001: 179.2035

Sheet Suppliers
A1: supplier_id | B1: supplier_name | C1: country
A2: 1 | B2: Robinson, Beasley and Hall | C2: Cambodia
A3: 2 | B3: Holmes, Duncan and Reed | C3: Croatia
A4: 3 | B4: Mendez-Miller | C4: Samoa
A5: 4 | B5: Martin, Dean and Glenn | C5: Cape Verde
A6: 5 | B6: Logan-Fernandez | C6: Madagascar
A7: 6 | B7: Dunn Ltd | C7: Iceland
A8: 7 | B8: Holloway-Mcconnell | C8: Jersey
A9: 8 | B9: Andrews-Jordan | C9: South Africa
A10: 9 | B10: Aguirre and Sons | C10: Saint Kitts and Nevis
A11: 10 | B11: Wilson, Jones and Gregory | C11: Venezuela
A12: 11 | B12: Cross Inc | C12: Azerbaijan
A13: 12 | B13: Yoder-Thompson | C13: Puerto Rico
... A51: 50 | B51: Waters-Robinson | C51: United Arab Emirates

Sheet Vehicles
A1: vehicle_id | B1: vehicle_type | C1: capacity_kg | D1: driver_name
A2: 1 | B2: Bike | C2: 1351 | D2: Lori Wilson
A3: 2 | B3: Drone | C3: 1852 | D3: Sherry Carney
A4: 3 | B4: Truck | C4: 626 | D4: Holly Gould
A5: 4 | B5: Drone | C5: 3498 | D5: Matthew Jackson
A6: 5 | B6: Van | C6: 3439 | D6: Mark Taylor
A7: 6 | B7: Bike | C7: 2810 | D7: Caitlyn Graves
A8: 7 | B8: Truck | C8: 4545 | D8: Jose Carney
A9: 8 | B9: Drone | C9: 3916 | D9: Troy Cooper
A10: 9 | B10: Truck | C10: 3506 | D10: James Hendricks
A11: 10 | B11: Van | C11: 610 | D11: Joseph Parks
A12: 11 | B12: Bike | C12: 1794 | D12: Pamela Leonard
A13: 12 | B13: Drone | C13: 3541 | D13: Eugene Brown
... A101: 100 | B101: Drone | C101: 934 | D101: Kyle Sharp
